[
    {
        "$type": "create_avatar",
        "type": "A_Img_Caps_Kinematic",
        "id": "a"
    },
    {
        "$type": "set_pass_masks",
        "pass_masks": [
            "_img"
        ],
        "avatar_id": "a"
    },
    {
        "$type": "set_render_order",
        "render_order": 100,
        "avatar_id": "a"
    },
    {
        "$type": "teleport_avatar_to",
        "position": {
            "x": 0,
            "y": 30,
            "z": 0
        },
        "avatar_id": "a"
    },
    {
        "$type": "look_at_position",
        "position": {
            "x": 0,
            "y": 0,
            "z": 0
        },
        "avatar_id": "a"
    },
    {
        "$type": "add_object",
        "name": "b04_banana",
        "url": "https://tdw-public.s3.amazonaws.com/models/linux/2018-2019.1/b04_banana",
        "scale_factor": 0.254,
        "position": {
            "x": 11.639787002695941,
            "y": 0.905102550983429,
            "z": -3.2990734962664567
        },
        "category": "banana",
        "id": 15753588,
        "affordance_points": []
    },
    {
        "$type": "set_kinematic_state",
        "id": 15753588,
        "is_kinematic": false,
        "use_gravity": true
    },
    {
        "$type": "set_mass",
        "mass": 6.032622914062813,
        "id": 15753588
    },
    {
        "$type": "set_physic_material",
        "dynamic_friction": 0.43,
        "static_friction": 0.47,
        "bounciness": 0.506,
        "id": 15753588
    },
    {
        "$type": "scale_object_and_mass",
        "scale_factor": {
            "x": 0.8,
            "y": 0.8,
            "z": 0.8
        },
        "id": 15753588
    },
    {
        "$type": "add_object",
        "name": "b05_executive_pen",
        "url": "https://tdw-public.s3.amazonaws.com/models/linux/2018-2019.1/b05_executive_pen",
        "scale_factor": 1.0,
        "position": {
            "x": -8.069501740439835,
            "y": 0.5740110874176025,
            "z": 2.2752063034684205
        },
        "category": "pen",
        "id": 4829413,
        "affordance_points": []
    },
    {
        "$type": "set_kinematic_state",
        "id": 4829413,
        "is_kinematic": false,
        "use_gravity": true
    },
    {
        "$type": "set_mass",
        "mass": 0.1,
        "id": 4829413
    },
    {
        "$type": "set_physic_material",
        "dynamic_friction": 0.43,
        "static_friction": 0.47,
        "bounciness": 0.6,
        "id": 4829413
    },
    {
        "$type": "scale_object_and_mass",
        "scale_factor": {
            "x": 2.4000000000000004,
            "y": 2.4000000000000004,
            "z": 2.4000000000000004
        },
        "id": 4829413
    },
    {
        "$type": "add_object",
        "name": "mouse_02_vray",
        "url": "https://tdw-public.s3.amazonaws.com/models/linux/2018-2019.1/mouse_02_vray",
        "scale_factor": 1.0,
        "position": {
            "x": -3.2264789908103078,
            "y": 0.931574285030365,
            "z": 3.976302254140136
        },
        "category": "computer mouse",
        "id": 13907984,
        "affordance_points": []
    },
    {
        "$type": "set_kinematic_state",
        "id": 13907984,
        "is_kinematic": false,
        "use_gravity": true
    },
    {
        "$type": "set_mass",
        "mass": 0.2,
        "id": 13907984
    },
    {
        "$type": "set_physic_material",
        "dynamic_friction": 0.3,
        "static_friction": 0.35,
        "bounciness": 0.5,
        "id": 13907984
    },
    {
        "$type": "scale_object_and_mass",
        "scale_factor": {
            "x": 1.2000000000000002,
            "y": 1.2000000000000002,
            "z": 1.2000000000000002
        },
        "id": 13907984
    },
    {
        "$type": "add_object",
        "name": "b04_banana",
        "url": "https://tdw-public.s3.amazonaws.com/models/linux/2018-2019.1/b04_banana",
        "scale_factor": 0.254,
        "position": {
            "x": -11.994472257174417,
            "y": 0.7253099083900452,
            "z": 4.597589441411053
        },
        "category": "banana",
        "id": 8414749,
        "affordance_points": []
    },
    {
        "$type": "set_kinematic_state",
        "id": 8414749,
        "is_kinematic": false,
        "use_gravity": true
    },
    {
        "$type": "set_mass",
        "mass": 6.032622914062813,
        "id": 8414749
    },
    {
        "$type": "set_physic_material",
        "dynamic_friction": 0.43,
        "static_friction": 0.47,
        "bounciness": 0.506,
        "id": 8414749
    },
    {
        "$type": "scale_object_and_mass",
        "scale_factor": {
            "x": 0.8,
            "y": 0.8,
            "z": 0.8
        },
        "id": 8414749
    },
    {
        "$type": "add_object",
        "name": "small_purse",
        "url": "https://tdw-public.s3.amazonaws.com/models/linux/2018-2019.1/small_purse",
        "scale_factor": 1.0,
        "position": {
            "x": -7.21062363298246,
            "y": 0.6115992069244385,
            "z": 0.9366901484422836
        },
        "category": "bag, handbag, pocketbook, purse",
        "id": 11506959,
        "affordance_points": []
    },
    {
        "$type": "set_kinematic_state",
        "id": 11506959,
        "is_kinematic": false,
        "use_gravity": true
    },
    {
        "$type": "set_mass",
        "mass": 1.0,
        "id": 11506959
    },
    {
        "$type": "set_physic_material",
        "dynamic_friction": 0.4,
        "static_friction": 0.43,
        "bounciness": 0.2,
        "id": 11506959
    },
    {
        "$type": "scale_object_and_mass",
        "scale_factor": {
            "x": 1.6,
            "y": 1.6,
            "z": 1.6
        },
        "id": 11506959
    },
    {
        "$type": "add_object",
        "name": "f10_apple_iphone_4",
        "url": "https://tdw-public.s3.amazonaws.com/models/linux/2018-2019.1/f10_apple_iphone_4",
        "scale_factor": 1.0,
        "position": {
            "x": -4.2727443491276516,
            "y": 0.9315773248672485,
            "z": 4.879286807251816
        },
        "category": "ipod",
        "id": 3480617,
        "affordance_points": []
    },
    {
        "$type": "set_kinematic_state",
        "id": 3480617,
        "is_kinematic": false,
        "use_gravity": true
    },
    {
        "$type": "set_mass",
        "mass": 0.25,
        "id": 3480617
    },
    {
        "$type": "set_physic_material",
        "dynamic_friction": 0.3,
        "static_friction": 0.35,
        "bounciness": 0.7,
        "id": 3480617
    },
    {
        "$type": "scale_object_and_mass",
        "scale_factor": {
            "x": 1.6,
            "y": 1.6,
            "z": 1.6
        },
        "id": 3480617
    },
    {
        "$type": "add_object",
        "name": "teatray",
        "url": "https://tdw-public.s3.amazonaws.com/models/linux/2018-2019.1/teatray",
        "scale_factor": 1.0,
        "position": {
            "x": -0.879153714964797,
            "y": 0.6175916194915771,
            "z": -1.7858323704256447
        },
        "category": "tea tray",
        "id": 16117260,
        "affordance_points": []
    },
    {
        "$type": "set_kinematic_state",
        "id": 16117260,
        "is_kinematic": false,
        "use_gravity": true
    },
    {
        "$type": "set_mass",
        "mass": 1.4337517321109772,
        "id": 16117260
    },
    {
        "$type": "set_physic_material",
        "dynamic_friction": 0.35,
        "static_friction": 0.37,
        "bounciness": 0.4,
        "id": 16117260
    },
    {
        "$type": "scale_object_and_mass",
        "scale_factor": {
            "x": 0.8,
            "y": 0.8,
            "z": 0.8
        },
        "id": 16117260
    },
    {
        "$type": "add_box_container",
        "id": 16117260,
        "container_id": 10815510,
        "position": {
            "x": 0,
            "y": 0.03384544,
            "z": 0
        },
        "tag": "inside",
        "half_extents": {
            "x": 0.271123485,
            "y": 0.028454845,
            "z": 0.192515605
        },
        "rotation": {
            "x": 0.0,
            "y": 0.0,
            "z": 0.0
        }
    },
    {
        "$type": "add_object",
        "name": "f10_apple_iphone_4",
        "url": "https://tdw-public.s3.amazonaws.com/models/linux/2018-2019.1/f10_apple_iphone_4",
        "scale_factor": 1.0,
        "position": {
            "x": 0.2426743723237042,
            "y": 0.7808550000190735,
            "z": 3.917273697124635
        },
        "category": "ipod",
        "id": 423967,
        "affordance_points": []
    },
    {
        "$type": "set_kinematic_state",
        "id": 423967,
        "is_kinematic": false,
        "use_gravity": true
    },
    {
        "$type": "set_mass",
        "mass": 0.25,
        "id": 423967
    },
    {
        "$type": "set_physic_material",
        "dynamic_friction": 0.3,
        "static_friction": 0.35,
        "bounciness": 0.7,
        "id": 423967
    },
    {
        "$type": "scale_object_and_mass",
        "scale_factor": {
            "x": 1.6,
            "y": 1.6,
            "z": 1.6
        },
        "id": 423967
    },
    {
        "$type": "add_object",
        "name": "b04_orange_00",
        "url": "https://tdw-public.s3.amazonaws.com/models/linux/2018-2019.1/b04_orange_00",
        "scale_factor": 0.1,
        "position": {
            "x": -7.209413973219035,
            "y": 0.6115992069244385,
            "z": 0.936562878794178
        },
        "category": "orange",
        "id": 13054520,
        "affordance_points": []
    },
    {
        "$type": "set_kinematic_state",
        "id": 13054520,
        "is_kinematic": false,
        "use_gravity": true
    },
    {
        "$type": "set_mass",
        "mass": 3.690280835144222,
        "id": 13054520
    },
    {
        "$type": "set_physic_material",
        "dynamic_friction": 0.47,
        "static_friction": 0.47,
        "bounciness": 0.378,
        "id": 13054520
    },
    {
        "$type": "scale_object_and_mass",
        "scale_factor": {
            "x": 0.8,
            "y": 0.8,
            "z": 0.8
        },
        "id": 13054520
    },
    {
        "$type": "add_object",
        "name": "b03_loafbread",
        "url": "https://tdw-public.s3.amazonaws.com/models/linux/2018-2019.1/b03_loafbread",
        "scale_factor": 1.0,
        "position": {
            "x": 11.639772035719604,
            "y": 0.905102550983429,
            "z": -3.300183169072096
        },
        "category": "bread",
        "id": 8030086,
        "affordance_points": []
    },
    {
        "$type": "set_kinematic_state",
        "id": 8030086,
        "is_kinematic": false,
        "use_gravity": true
    },
    {
        "$type": "set_mass",
        "mass": 5.391221772879362,
        "id": 8030086
    },
    {
        "$type": "set_physic_material",
        "dynamic_friction": 0.3,
        "static_friction": 0.35,
        "bounciness": 0.548,
        "id": 8030086
    },
    {
        "$type": "scale_object_and_mass",
        "scale_factor": {
            "x": 0.5599999999999999,
            "y": 0.5599999999999999,
            "z": 0.5599999999999999
        },
        "id": 8030086
    },
    {
        "$type": "add_object",
        "name": "key_brass",
        "url": "https://tdw-public.s3.amazonaws.com/models/linux/2020.2/key_brass",
        "scale_factor": 1,
        "position": {
            "x": -0.2844417139378049,
            "y": 0.7808817625045776,
            "z": 3.0626660400820986
        },
        "category": "key",
        "id": 2320237,
        "affordance_points": []
    },
    {
        "$type": "set_kinematic_state",
        "id": 2320237,
        "is_kinematic": false,
        "use_gravity": true
    },
    {
        "$type": "set_mass",
        "mass": 0.1,
        "id": 2320237
    },
    {
        "$type": "set_physic_material",
        "dynamic_friction": 0.43,
        "static_friction": 0.47,
        "bounciness": 0.6,
        "id": 2320237
    },
    {
        "$type": "scale_object_and_mass",
        "scale_factor": {
            "x": 3.2,
            "y": 3.2,
            "z": 3.2
        },
        "id": 2320237
    },
    {
        "$type": "add_object",
        "name": "basket_18inx18inx12iin_plastic_lattice",
        "url": "https://tdw-public.s3.amazonaws.com/models/linux/2019.2/basket_18inx18inx12iin_plastic_lattice",
        "scale_factor": 1,
        "position": {
            "x": 5.796191219558817,
            "y": 0.7469063997268677,
            "z": -4.872965663021569
        },
        "category": "basket",
        "id": 10591075,
        "affordance_points": [
            {
                "x": -0.2285,
                "y": 0.305,
                "z": 0.0
            },
            {
                "x": 0.2285,
                "y": 0.305,
                "z": 0.0
            },
            {
                "x": 0,
                "y": 0.305,
                "z": 0.2285
            },
            {
                "x": 0,
                "y": 0.305,
                "z": -0.2285
            }
        ]
    },
    {
        "$type": "set_kinematic_state",
        "id": 10591075,
        "is_kinematic": false,
        "use_gravity": true
    },
    {
        "$type": "set_mass",
        "mass": 5.0,
        "id": 10591075
    },
    {
        "$type": "set_physic_material",
        "dynamic_friction": 0.45,
        "static_friction": 0.48,
        "bounciness": 0.5,
        "id": 10591075
    },
    {
        "$type": "scale_object_and_mass",
        "scale_factor": {
            "x": 0.8,
            "y": 0.8,
            "z": 0.8
        },
        "id": 10591075
    },
    {
        "$type": "add_box_container",
        "id": 10591075,
        "container_id": 3959045,
        "position": {
            "x": 0,
            "y": 0.15855929,
            "z": 0
        },
        "tag": "inside",
        "half_extents": {
            "x": 0.219846255,
            "y": 0.14644071,
            "z": 0.219889125
        },
        "rotation": {
            "x": 0.0,
            "y": 0.0,
            "z": 0.0
        }
    },
    {
        "$type": "add_object",
        "name": "apple_ipod_touch_yellow_vray",
        "url": "https://tdw-public.s3.amazonaws.com/models/linux/2018-2019.1/apple_ipod_touch_yellow_vray",
        "scale_factor": 1.0,
        "position": {
            "x": 1.0033379301482095,
            "y": 0.7909574508666992,
            "z": 3.0251386732852135
        },
        "category": "ipod",
        "id": 57397,
        "affordance_points": []
    },
    {
        "$type": "set_kinematic_state",
        "id": 57397,
        "is_kinematic": false,
        "use_gravity": true
    },
    {
        "$type": "set_mass",
        "mass": 0.19,
        "id": 57397
    },
    {
        "$type": "set_physic_material",
        "dynamic_friction": 0.3,
        "static_friction": 0.35,
        "bounciness": 0.7,
        "id": 57397
    },
    {
        "$type": "scale_object_and_mass",
        "scale_factor": {
            "x": 1.6,
            "y": 1.6,
            "z": 1.6
        },
        "id": 57397
    },
    {
        "$type": "add_object",
        "name": "f10_apple_iphone_4",
        "url": "https://tdw-public.s3.amazonaws.com/models/linux/2018-2019.1/f10_apple_iphone_4",
        "scale_factor": 1.0,
        "position": {
            "x": 1.0054654728301835,
            "y": 0.7909574508666992,
            "z": 3.0056593062453105
        },
        "category": "ipod",
        "id": 9881640,
        "affordance_points": []
    },
    {
        "$type": "set_kinematic_state",
        "id": 9881640,
        "is_kinematic": false,
        "use_gravity": true
    },
    {
        "$type": "set_mass",
        "mass": 0.25,
        "id": 9881640
    },
    {
        "$type": "set_physic_material",
        "dynamic_friction": 0.3,
        "static_friction": 0.35,
        "bounciness": 0.7,
        "id": 9881640
    },
    {
        "$type": "scale_object_and_mass",
        "scale_factor": {
            "x": 1.6,
            "y": 1.6,
            "z": 1.6
        },
        "id": 9881640
    },
    {
        "$type": "add_object",
        "name": "apple",
        "url": "https://tdw-public.s3.amazonaws.com/models/linux/2018-2019.1/apple",
        "scale_factor": 0.08862933,
        "position": {
            "x": -3.6002880317422314,
            "y": 0.4514075517654419,
            "z": 4.741737040241754
        },
        "category": "apple",
        "id": 11756991,
        "affordance_points": []
    },
    {
        "$type": "set_kinematic_state",
        "id": 11756991,
        "is_kinematic": false,
        "use_gravity": true
    },
    {
        "$type": "set_mass",
        "mass": 2.30235627386719,
        "id": 11756991
    },
    {
        "$type": "set_physic_material",
        "dynamic_friction": 0.43,
        "static_friction": 0.47,
        "bounciness": 0.561,
        "id": 11756991
    },
    {
        "$type": "scale_object_and_mass",
        "scale_factor": {
            "x": 0.96,
            "y": 0.96,
            "z": 0.96
        },
        "id": 11756991
    },
    {
        "$type": "add_object",
        "name": "b05_calculator",
        "url": "https://tdw-public.s3.amazonaws.com/models/linux/2018-2019.1/b05_calculator",
        "scale_factor": 0.001,
        "position": {
            "x": -5.350868216786921,
            "y": 0.8967773914337158,
            "z": 4.469226478351569
        },
        "category": "calculator",
        "id": 8269026,
        "affordance_points": []
    },
    {
        "$type": "set_kinematic_state",
        "id": 8269026,
        "is_kinematic": false,
        "use_gravity": true
    },
    {
        "$type": "set_mass",
        "mass": 0.2,
        "id": 8269026
    },
    {
        "$type": "set_physic_material",
        "dynamic_friction": 0.3,
        "static_friction": 0.35,
        "bounciness": 0.6,
        "id": 8269026
    },
    {
        "$type": "scale_object_and_mass",
        "scale_factor": {
            "x": 1.6,
            "y": 1.6,
            "z": 1.6
        },
        "id": 8269026
    },
    {
        "$type": "add_object",
        "name": "plate06",
        "url": "https://tdw-public.s3.amazonaws.com/models/linux/2018-2019.1/plate06",
        "scale_factor": 1.0,
        "position": {
            "x": 0.020527537350860575,
            "y": 0.7326276898384094,
            "z": 2.7537538287187027
        },
        "category": "plate",
        "id": 15301648,
        "affordance_points": []
    },
    {
        "$type": "set_kinematic_state",
        "id": 15301648,
        "is_kinematic": false,
        "use_gravity": true
    },
    {
        "$type": "set_mass",
        "mass": 1.801538816653192,
        "id": 15301648
    },
    {
        "$type": "set_physic_material",
        "dynamic_friction": 0.47,
        "static_friction": 0.47,
        "bounciness": 0.625,
        "id": 15301648
    },
    {
        "$type": "scale_object_and_mass",
        "scale_factor": {
            "x": 1.7600000000000002,
            "y": 1.7600000000000002,
            "z": 1.7600000000000002
        },
        "id": 15301648
    },
    {
        "$type": "add_cylinder_container",
        "id": 15301648,
        "container_id": 11520003,
        "position": {
            "x": 2.733e-05,
            "y": 0.01210938,
            "z": 3.13e-06
        },
        "tag": "on",
        "radius": 0.08634067,
        "height": 0.01,
        "rotation": {
            "x": 0.0,
            "y": 0.0,
            "z": 0.0
        }
    },
    {
        "$type": "add_object",
        "name": "b05_executive_pen",
        "url": "https://tdw-public.s3.amazonaws.com/models/linux/2018-2019.1/b05_executive_pen",
        "scale_factor": 1.0,
        "position": {
            "x": -3.2265318834852152,
            "y": 0.931574285030365,
            "z": 3.976839719104955
        },
        "category": "pen",
        "id": 410755,
        "affordance_points": []
    },
    {
        "$type": "set_kinematic_state",
        "id": 410755,
        "is_kinematic": false,
        "use_gravity": true
    },
    {
        "$type": "set_mass",
        "mass": 0.1,
        "id": 410755
    },
    {
        "$type": "set_physic_material",
        "dynamic_friction": 0.43,
        "static_friction": 0.47,
        "bounciness": 0.6,
        "id": 410755
    },
    {
        "$type": "scale_object_and_mass",
        "scale_factor": {
            "x": 2.4000000000000004,
            "y": 2.4000000000000004,
            "z": 2.4000000000000004
        },
        "id": 410755
    },
    {
        "$type": "add_object",
        "name": "basket_18inx18inx12iin_wood_mesh",
        "url": "https://tdw-public.s3.amazonaws.com/models/linux/2019.2/basket_18inx18inx12iin_wood_mesh",
        "scale_factor": 1,
        "position": {
            "x": -2.114776979168959,
            "y": 0.8975381255149841,
            "z": -0.4844628855652998
        },
        "category": "basket",
        "id": 9655455,
        "affordance_points": [
            {
                "x": -0.2285,
                "y": 0.305,
                "z": 0.0
            },
            {
                "x": 0.2285,
                "y": 0.305,
                "z": 0.0
            },
            {
                "x": 0,
                "y": 0.305,
                "z": 0.2285
            },
            {
                "x": 0,
                "y": 0.305,
                "z": -0.2285
            }
        ]
    },
    {
        "$type": "set_kinematic_state",
        "id": 9655455,
        "is_kinematic": false,
        "use_gravity": true
    },
    {
        "$type": "set_mass",
        "mass": 5.0,
        "id": 9655455
    },
    {
        "$type": "set_physic_material",
        "dynamic_friction": 0.45,
        "static_friction": 0.48,
        "bounciness": 0.5,
        "id": 9655455
    },
    {
        "$type": "scale_object_and_mass",
        "scale_factor": {
            "x": 0.8,
            "y": 0.8,
            "z": 0.8
        },
        "id": 9655455
    },
    {
        "$type": "add_box_container",
        "id": 9655455,
        "container_id": 7148361,
        "position": {
            "x": 0,
            "y": 0.1585595,
            "z": 0
        },
        "tag": "inside",
        "half_extents": {
            "x": 0.21984552,
            "y": 0.146440505,
            "z": 0.219888405
        },
        "rotation": {
            "x": 0.0,
            "y": 0.0,
            "z": 0.0
        }
    },
    {
        "$type": "add_object",
        "name": "b03_burger",
        "url": "https://tdw-public.s3.amazonaws.com/models/linux/2018-2019.1/b03_burger",
        "scale_factor": 0.1350851,
        "position": {
            "x": 8.065186227477223,
            "y": 0.8470534682273865,
            "z": -1.9761618399330787
        },
        "category": "sandwich",
        "id": 13990658,
        "affordance_points": []
    },
    {
        "$type": "set_kinematic_state",
        "id": 13990658,
        "is_kinematic": false,
        "use_gravity": true
    },
    {
        "$type": "set_mass",
        "mass": 2.2601000091526657,
        "id": 13990658
    },
    {
        "$type": "set_physic_material",
        "dynamic_friction": 0.65,
        "static_friction": 0.68,
        "bounciness": 0.475,
        "id": 13990658
    },
    {
        "$type": "scale_object_and_mass",
        "scale_factor": {
            "x": 0.96,
            "y": 0.96,
            "z": 0.96
        },
        "id": 13990658
    },
    {
        "$type": "add_object",
        "name": "mouse_02_vray",
        "url": "https://tdw-public.s3.amazonaws.com/models/linux/2018-2019.1/mouse_02_vray",
        "scale_factor": 1.0,
        "position": {
            "x": -5.9997787672896505,
            "y": 0.8967773914337158,
            "z": 4.8915513268098065
        },
        "category": "computer mouse",
        "id": 11190115,
        "affordance_points": []
    },
    {
        "$type": "set_kinematic_state",
        "id": 11190115,
        "is_kinematic": false,
        "use_gravity": true
    },
    {
        "$type": "set_mass",
        "mass": 0.2,
        "id": 11190115
    },
    {
        "$type": "set_physic_material",
        "dynamic_friction": 0.3,
        "static_friction": 0.35,
        "bounciness": 0.5,
        "id": 11190115
    },
    {
        "$type": "scale_object_and_mass",
        "scale_factor": {
            "x": 1.2000000000000002,
            "y": 1.2000000000000002,
            "z": 1.2000000000000002
        },
        "id": 11190115
    },
    {
        "$type": "add_object",
        "name": "small_purse",
        "url": "https://tdw-public.s3.amazonaws.com/models/linux/2018-2019.1/small_purse",
        "scale_factor": 1.0,
        "position": {
            "x": -0.2623910366610289,
            "y": 0.6778541207313538,
            "z": -2.629629548530508
        },
        "category": "bag, handbag, pocketbook, purse",
        "id": 2798326,
        "affordance_points": []
    },
    {
        "$type": "set_kinematic_state",
        "id": 2798326,
        "is_kinematic": false,
        "use_gravity": true
    },
    {
        "$type": "set_mass",
        "mass": 1.0,
        "id": 2798326
    },
    {
        "$type": "set_physic_material",
        "dynamic_friction": 0.4,
        "static_friction": 0.43,
        "bounciness": 0.2,
        "id": 2798326
    },
    {
        "$type": "scale_object_and_mass",
        "scale_factor": {
            "x": 1.6,
            "y": 1.6,
            "z": 1.6
        },
        "id": 2798326
    },
    {
        "$type": "add_object",
        "name": "pencil_all",
        "url": "https://tdw-public.s3.amazonaws.com/models/linux/2018-2019.1/pencil_all",
        "scale_factor": 1.0,
        "position": {
            "x": 6.038716353397296,
            "y": 0.5739852786064148,
            "z": -0.3853980489761475
        },
        "category": "pencil",
        "id": 15390314,
        "affordance_points": []
    },
    {
        "$type": "set_kinematic_state",
        "id": 15390314,
        "is_kinematic": false,
        "use_gravity": true
    },
    {
        "$type": "set_mass",
        "mass": 0.2,
        "id": 15390314
    },
    {
        "$type": "set_physic_material",
        "dynamic_friction": 0.35,
        "static_friction": 0.37,
        "bounciness": 0.5,
        "id": 15390314
    },
    {
        "$type": "scale_object_and_mass",
        "scale_factor": {
            "x": 0.96,
            "y": 0.96,
            "z": 0.96
        },
        "id": 15390314
    },
    {
        "$type": "add_object",
        "name": "apple",
        "url": "https://tdw-public.s3.amazonaws.com/models/linux/2018-2019.1/apple",
        "scale_factor": 0.08862933,
        "position": {
            "x": 0.6661316442712251,
            "y": 0.7326276898384094,
            "z": 2.7931368669139887
        },
        "category": "apple",
        "id": 13575603,
        "affordance_points": []
    },
    {
        "$type": "set_kinematic_state",
        "id": 13575603,
        "is_kinematic": false,
        "use_gravity": true
    },
    {
        "$type": "set_mass",
        "mass": 2.30235627386719,
        "id": 13575603
    },
    {
        "$type": "set_physic_material",
        "dynamic_friction": 0.43,
        "static_friction": 0.47,
        "bounciness": 0.561,
        "id": 13575603
    },
    {
        "$type": "scale_object_and_mass",
        "scale_factor": {
            "x": 0.96,
            "y": 0.96,
            "z": 0.96
        },
        "id": 13575603
    },
    {
        "$type": "add_object",
        "name": "b05_calculator",
        "url": "https://tdw-public.s3.amazonaws.com/models/linux/2018-2019.1/b05_calculator",
        "scale_factor": 0.001,
        "position": {
            "x": 6.032267258067019,
            "y": 0.5739852786064148,
            "z": 0.03722267273612212
        },
        "category": "calculator",
        "id": 2278057,
        "affordance_points": []
    },
    {
        "$type": "set_kinematic_state",
        "id": 2278057,
        "is_kinematic": false,
        "use_gravity": true
    },
    {
        "$type": "set_mass",
        "mass": 0.2,
        "id": 2278057
    },
    {
        "$type": "set_physic_material",
        "dynamic_friction": 0.3,
        "static_friction": 0.35,
        "bounciness": 0.6,
        "id": 2278057
    },
    {
        "$type": "scale_object_and_mass",
        "scale_factor": {
            "x": 1.6,
            "y": 1.6,
            "z": 1.6
        },
        "id": 2278057
    },
    {
        "$type": "add_object",
        "name": "b04_bowl_smooth",
        "url": "https://tdw-public.s3.amazonaws.com/models/linux/2018-2019.1/b04_bowl_smooth",
        "scale_factor": 1.0,
        "position": {
            "x": -0.5054752641554946,
            "y": 0.6175916194915771,
            "z": -1.8176821075385616
        },
        "category": "bowl",
        "id": 2071792,
        "affordance_points": []
    },
    {
        "$type": "set_kinematic_state",
        "id": 2071792,
        "is_kinematic": false,
        "use_gravity": true
    },
    {
        "$type": "set_mass",
        "mass": 5.5,
        "id": 2071792
    },
    {
        "$type": "set_physic_material",
        "dynamic_friction": 0.47,
        "static_friction": 0.47,
        "bounciness": 0.625,
        "id": 2071792
    },
    {
        "$type": "scale_object_and_mass",
        "scale_factor": {
            "x": 1.7600000000000002,
            "y": 1.7600000000000002,
            "z": 1.7600000000000002
        },
        "id": 2071792
    },
    {
        "$type": "add_cylinder_container",
        "id": 2071792,
        "container_id": 5111999,
        "position": {
            "x": 9.649e-05,
            "y": 0.04461811,
            "z": 0.00034404
        },
        "tag": "inside",
        "radius": 0.09662219,
        "height": 0.07422157,
        "rotation": {
            "x": 0.0,
            "y": 0.0,
            "z": 0.0
        }
    },
    {
        "$type": "add_object",
        "name": "apple_ipod_touch_yellow_vray",
        "url": "https://tdw-public.s3.amazonaws.com/models/linux/2018-2019.1/apple_ipod_touch_yellow_vray",
        "scale_factor": 1.0,
        "position": {
            "x": 0.005354386804802408,
            "y": 0.7326276898384094,
            "z": 3.497041624067482
        },
        "category": "ipod",
        "id": 4570068,
        "affordance_points": []
    },
    {
        "$type": "set_kinematic_state",
        "id": 4570068,
        "is_kinematic": false,
        "use_gravity": true
    },
    {
        "$type": "set_mass",
        "mass": 0.19,
        "id": 4570068
    },
    {
        "$type": "set_physic_material",
        "dynamic_friction": 0.3,
        "static_friction": 0.35,
        "bounciness": 0.7,
        "id": 4570068
    },
    {
        "$type": "scale_object_and_mass",
        "scale_factor": {
            "x": 1.6,
            "y": 1.6,
            "z": 1.6
        },
        "id": 4570068
    },
    {
        "$type": "add_object",
        "name": "basket_18inx18inx12iin_wicker",
        "url": "https://tdw-public.s3.amazonaws.com/models/linux/2019.2/basket_18inx18inx12iin_wicker",
        "scale_factor": 1,
        "position": {
            "x": -2.1317641601453508,
            "y": 0.8975381255149841,
            "z": -0.48542369357837695
        },
        "category": "basket",
        "id": 593898,
        "affordance_points": [
            {
                "x": -0.2285,
                "y": 0.305,
                "z": 0.0
            },
            {
                "x": 0.2285,
                "y": 0.305,
                "z": 0.0
            },
            {
                "x": 0,
                "y": 0.305,
                "z": 0.2285
            },
            {
                "x": 0,
                "y": 0.305,
                "z": -0.2285
            }
        ]
    },
    {
        "$type": "set_kinematic_state",
        "id": 593898,
        "is_kinematic": false,
        "use_gravity": true
    },
    {
        "$type": "set_mass",
        "mass": 5.0,
        "id": 593898
    },
    {
        "$type": "set_physic_material",
        "dynamic_friction": 0.45,
        "static_friction": 0.48,
        "bounciness": 0.5,
        "id": 593898
    },
    {
        "$type": "scale_object_and_mass",
        "scale_factor": {
            "x": 0.8,
            "y": 0.8,
            "z": 0.8
        },
        "id": 593898
    },
    {
        "$type": "add_box_container",
        "id": 593898,
        "container_id": 4536570,
        "position": {
            "x": 0,
            "y": 0.15855946,
            "z": 0
        },
        "tag": "inside",
        "half_extents": {
            "x": 0.21984584,
            "y": 0.14644054,
            "z": 0.2198887
        },
        "rotation": {
            "x": 0.0,
            "y": 0.0,
            "z": 0.0
        }
    },
    {
        "$type": "add_object",
        "name": "bread",
        "url": "https://tdw-public.s3.amazonaws.com/models/linux/2018-2019.1/bread",
        "scale_factor": 1.0,
        "position": {
            "x": -5.821618472217246,
            "y": 1.0279126167297363,
            "z": 3.9102568123707706
        },
        "category": "bread",
        "id": 5119430,
        "affordance_points": []
    },
    {
        "$type": "set_kinematic_state",
        "id": 5119430,
        "is_kinematic": false,
        "use_gravity": true
    },
    {
        "$type": "set_mass",
        "mass": 3.161416675429791,
        "id": 5119430
    },
    {
        "$type": "set_physic_material",
        "dynamic_friction": 0.47,
        "static_friction": 0.47,
        "bounciness": 0.464,
        "id": 5119430
    },
    {
        "$type": "scale_object_and_mass",
        "scale_factor": {
            "x": 0.6400000000000001,
            "y": 0.6400000000000001,
            "z": 0.6400000000000001
        },
        "id": 5119430
    },
    {
        "$type": "add_object",
        "name": "pencil_all",
        "url": "https://tdw-public.s3.amazonaws.com/models/linux/2018-2019.1/pencil_all",
        "scale_factor": 1.0,
        "position": {
            "x": 10.449755135941853,
            "y": 0.2889782786369324,
            "z": -3.2146936128132695
        },
        "category": "pencil",
        "id": 3083120,
        "affordance_points": []
    },
    {
        "$type": "set_kinematic_state",
        "id": 3083120,
        "is_kinematic": false,
        "use_gravity": true
    },
    {
        "$type": "set_mass",
        "mass": 0.2,
        "id": 3083120
    },
    {
        "$type": "set_physic_material",
        "dynamic_friction": 0.35,
        "static_friction": 0.37,
        "bounciness": 0.5,
        "id": 3083120
    },
    {
        "$type": "scale_object_and_mass",
        "scale_factor": {
            "x": 0.96,
            "y": 0.96,
            "z": 0.96
        },
        "id": 3083120
    },
    {
        "$type": "add_object",
        "name": "b03_loafbread",
        "url": "https://tdw-public.s3.amazonaws.com/models/linux/2018-2019.1/b03_loafbread",
        "scale_factor": 1.0,
        "position": {
            "x": -11.959912894015787,
            "y": 0.7253099083900452,
            "z": 4.934675281555684
        },
        "category": "bread",
        "id": 7106033,
        "affordance_points": []
    },
    {
        "$type": "set_kinematic_state",
        "id": 7106033,
        "is_kinematic": false,
        "use_gravity": true
    },
    {
        "$type": "set_mass",
        "mass": 5.391221772879362,
        "id": 7106033
    },
    {
        "$type": "set_physic_material",
        "dynamic_friction": 0.3,
        "static_friction": 0.35,
        "bounciness": 0.548,
        "id": 7106033
    },
    {
        "$type": "scale_object_and_mass",
        "scale_factor": {
            "x": 0.5599999999999999,
            "y": 0.5599999999999999,
            "z": 0.5599999999999999
        },
        "id": 7106033
    },
    {
        "$type": "add_object",
        "name": "f10_apple_iphone_4",
        "url": "https://tdw-public.s3.amazonaws.com/models/linux/2018-2019.1/f10_apple_iphone_4",
        "scale_factor": 1.0,
        "position": {
            "x": -1.0020537451572826,
            "y": 0.5808451175689697,
            "z": -5.190089508692546
        },
        "category": "ipod",
        "id": 12387988,
        "affordance_points": []
    },
    {
        "$type": "set_kinematic_state",
        "id": 12387988,
        "is_kinematic": false,
        "use_gravity": true
    },
    {
        "$type": "set_mass",
        "mass": 0.25,
        "id": 12387988
    },
    {
        "$type": "set_physic_material",
        "dynamic_friction": 0.3,
        "static_friction": 0.35,
        "bounciness": 0.7,
        "id": 12387988
    },
    {
        "$type": "scale_object_and_mass",
        "scale_factor": {
            "x": 1.6,
            "y": 1.6,
            "z": 1.6
        },
        "id": 12387988
    },
    {
        "$type": "add_object",
        "name": "b04_orange_00",
        "url": "https://tdw-public.s3.amazonaws.com/models/linux/2018-2019.1/b04_orange_00",
        "scale_factor": 0.1,
        "position": {
            "x": -5.816381904784521,
            "y": 1.0279126167297363,
            "z": 4.190330532234947
        },
        "category": "orange",
        "id": 15824023,
        "affordance_points": []
    },
    {
        "$type": "set_kinematic_state",
        "id": 15824023,
        "is_kinematic": false,
        "use_gravity": true
    },
    {
        "$type": "set_mass",
        "mass": 3.690280835144222,
        "id": 15824023
    },
    {
        "$type": "set_physic_material",
        "dynamic_friction": 0.47,
        "static_friction": 0.47,
        "bounciness": 0.378,
        "id": 15824023
    },
    {
        "$type": "scale_object_and_mass",
        "scale_factor": {
            "x": 0.8,
            "y": 0.8,
            "z": 0.8
        },
        "id": 15824023
    },
    {
        "$type": "add_object",
        "name": "bread",
        "url": "https://tdw-public.s3.amazonaws.com/models/linux/2018-2019.1/bread",
        "scale_factor": 1.0,
        "position": {
            "x": -2.1841937927557797,
            "y": 1.0439610481262207,
            "z": -1.342669801436822
        },
        "category": "bread",
        "id": 12090822,
        "affordance_points": []
    },
    {
        "$type": "set_kinematic_state",
        "id": 12090822,
        "is_kinematic": false,
        "use_gravity": true
    },
    {
        "$type": "set_mass",
        "mass": 3.161416675429791,
        "id": 12090822
    },
    {
        "$type": "set_physic_material",
        "dynamic_friction": 0.47,
        "static_friction": 0.47,
        "bounciness": 0.464,
        "id": 12090822
    },
    {
        "$type": "scale_object_and_mass",
        "scale_factor": {
            "x": 0.6400000000000001,
            "y": 0.6400000000000001,
            "z": 0.6400000000000001
        },
        "id": 12090822
    },
    {
        "$type": "add_object",
        "name": "b04_orange_00",
        "url": "https://tdw-public.s3.amazonaws.com/models/linux/2018-2019.1/b04_orange_00",
        "scale_factor": 0.1,
        "position": {
            "x": 7.7276904775375055,
            "y": 0.7469063997268677,
            "z": -5.331817625544409
        },
        "category": "orange",
        "id": 16173729,
        "affordance_points": []
    },
    {
        "$type": "set_kinematic_state",
        "id": 16173729,
        "is_kinematic": false,
        "use_gravity": true
    },
    {
        "$type": "set_mass",
        "mass": 3.690280835144222,
        "id": 16173729
    },
    {
        "$type": "set_physic_material",
        "dynamic_friction": 0.47,
        "static_friction": 0.47,
        "bounciness": 0.378,
        "id": 16173729
    },
    {
        "$type": "scale_object_and_mass",
        "scale_factor": {
            "x": 0.8,
            "y": 0.8,
            "z": 0.8
        },
        "id": 16173729
    },
    {
        "$type": "add_object",
        "name": "bread",
        "url": "https://tdw-public.s3.amazonaws.com/models/linux/2018-2019.1/bread",
        "scale_factor": 1.0,
        "position": {
            "x": -4.236331604714884,
            "y": 0.614704430103302,
            "z": 0.680487757815086
        },
        "category": "bread",
        "id": 8946488,
        "affordance_points": []
    },
    {
        "$type": "set_kinematic_state",
        "id": 8946488,
        "is_kinematic": false,
        "use_gravity": true
    },
    {
        "$type": "set_mass",
        "mass": 3.161416675429791,
        "id": 8946488
    },
    {
        "$type": "set_physic_material",
        "dynamic_friction": 0.47,
        "static_friction": 0.47,
        "bounciness": 0.464,
        "id": 8946488
    },
    {
        "$type": "scale_object_and_mass",
        "scale_factor": {
            "x": 0.6400000000000001,
            "y": 0.6400000000000001,
            "z": 0.6400000000000001
        },
        "id": 8946488
    },
    {
        "$type": "add_object",
        "name": "b03_burger",
        "url": "https://tdw-public.s3.amazonaws.com/models/linux/2018-2019.1/b03_burger",
        "scale_factor": 0.1350851,
        "position": {
            "x": 0.2442252618209718,
            "y": 0.7808958292007446,
            "z": 2.4510337403317366
        },
        "category": "sandwich",
        "id": 10742372,
        "affordance_points": []
    },
    {
        "$type": "set_kinematic_state",
        "id": 10742372,
        "is_kinematic": false,
        "use_gravity": true
    },
    {
        "$type": "set_mass",
        "mass": 2.2601000091526657,
        "id": 10742372
    },
    {
        "$type": "set_physic_material",
        "dynamic_friction": 0.65,
        "static_friction": 0.68,
        "bounciness": 0.475,
        "id": 10742372
    },
    {
        "$type": "scale_object_and_mass",
        "scale_factor": {
            "x": 0.96,
            "y": 0.96,
            "z": 0.96
        },
        "id": 10742372
    },
    {
        "$type": "set_img_pass_encoding",
        "value": false
    },
    {
        "$type": "set_pass_masks",
        "pass_masks": [
            "_img"
        ],
        "avatar_id": "a"
    },
    {
        "$type": "send_images",
        "frequency": "once",
        "ids": [
            "a"
        ]
    }
]