[
    {
        "$type": "add_scene",
        "name": "suburb_scene_2023",
        "url": "https://tdw-public.s3.amazonaws.com/scenes/linux/2020.3/suburb_scene_2023"
    },
    {
        "$type": "set_screen_size",
        "width": 512,
        "height": 512
    },
    {
        "$type": "create_avatar",
        "type": "A_Img_Caps_Kinematic",
        "id": "teaser"
    },
    {
        "$type": "set_pass_masks",
        "pass_masks": [
            "_img"
        ],
        "avatar_id": "teaser"
    },
    {
        "$type": "set_render_order",
        "render_order": 111,
        "avatar_id": "teaser"
    },
    {
        "$type": "teleport_avatar_to",
        "position": {
            "x": 27,
            "y": 5,
            "z": 0.7
        },
        "avatar_id": "teaser"
    },
    {
        "$type": "look_at_position",
        "position": {
            "x": 0,
            "y": 0,
            "z": 0.7
        },
        "avatar_id": "teaser"
    },
    {
        "$type": "send_log_messages"
    },
    {
        "$type": "set_field_of_view",
        "avatar_id": "teaser",
        "field_of_view": 80
    },
    {
        "$type": "set_pass_masks",
        "pass_masks": [
            "_img"
        ],
        "avatar_id": "teaser"
    },
    {
        "$type": "add_object",
        "name": "b01_tent",
        "url": "file://local_asset/Linux/b01_tent",
        "scale_factor": 1.0,
        "position": {
            "x": 10.0,
            "y": 0.0,
            "z": -2.5
        },
        "rotation": {
            "x": 0.0,
            "y": 90.0,
            "z": 0.0
        },
        "category": "tent",
        "id": 16433206,
        "affordance_points": []
    },
    {
        "$type": "set_kinematic_state",
        "id": 16433206,
        "is_kinematic": true
    },
    {
        "$type": "scale_object",
        "id": 16433206,
        "scale_factor": {
            "x": 0.4,
            "y": 1.0,
            "z": 0.8
        }
    },
    {
        "$type": "add_object",
        "name": "4ft_wood_shelving",
        "url": "file://local_asset/Linux/4ft_wood_shelving",
        "scale_factor": 1,
        "position": {
            "x": 9.3,
            "y": 0.0,
            "z": -2.0
        },
        "rotation": {
            "x": 0.0,
            "y": 90.0,
            "z": 0.0
        },
        "category": "shelf",
        "id": 1809052,
        "affordance_points": [
            {
                "x": -0.17737410962581635,
                "y": 1.0045626163482666,
                "z": 0.47309038043022156
            },
            {
                "x": 0.18099889159202576,
                "y": 1.008817434310913,
                "z": 0.47308892011642456
            },
            {
                "x": 0.17106591165065765,
                "y": 0.5919831395149231,
                "z": 0.4730895161628723
            },
            {
                "x": -0.17273925244808197,
                "y": 0.5780029296875,
                "z": 0.4730893075466156
            },
            {
                "x": 0.1752769649028778,
                "y": 0.20902684330940247,
                "z": 0.4730892777442932
            },
            {
                "x": -0.18031492829322815,
                "y": 0.20690900087356567,
                "z": 0.4730876088142395
            },
            {
                "x": 0.18165987730026245,
                "y": 0.20033997297286987,
                "z": -0.4733772873878479
            },
            {
                "x": -0.17170123755931854,
                "y": 0.21212810277938843,
                "z": -0.4733791947364807
            },
            {
                "x": 0.1702507734298706,
                "y": 0.558048665523529,
                "z": -0.4733777642250061
            },
            {
                "x": -0.1780988872051239,
                "y": 0.5678866505622864,
                "z": -0.4733792841434479
            },
            {
                "x": 0.17671309411525726,
                "y": 1.0124404430389404,
                "z": -0.4733796715736389
            },
            {
                "x": -0.17419706284999847,
                "y": 0.9986633658409119,
                "z": -0.4733791649341583
            },
            {
                "x": -0.17738457024097443,
                "y": 1.180309772491455,
                "z": -0.054380740970373154
            },
            {
                "x": -0.17790313065052032,
                "y": 0.7969714403152466,
                "z": -0.012365326285362244
            },
            {
                "x": -0.1779211312532425,
                "y": 0.3967873454093933,
                "z": -0.007543210871517658
            },
            {
                "x": 0.17936904728412628,
                "y": 0.3968244791030884,
                "z": 0.02620852179825306
            },
            {
                "x": 0.17935426533222198,
                "y": 0.7932231426239014,
                "z": 0.021726932376623154
            },
            {
                "x": 0.17936904728412628,
                "y": 1.187669277191162,
                "z": 0.027799217030405998
            }
        ]
    },
    {
        "$type": "set_kinematic_state",
        "id": 1809052,
        "is_kinematic": true
    },
    {
        "$type": "scale_object",
        "id": 1809052,
        "scale_factor": {
            "x": 1.0,
            "y": 0.8,
            "z": 1.2
        }
    },
    {
        "$type": "add_object",
        "name": "4ft_wood_shelving",
        "url": "file://local_asset/Linux/4ft_wood_shelving",
        "scale_factor": 1,
        "position": {
            "x": 10.7,
            "y": 0.0,
            "z": -2.0
        },
        "rotation": {
            "x": 0.0,
            "y": 90.0,
            "z": 0.0
        },
        "category": "shelf",
        "id": 6767665,
        "affordance_points": [
            {
                "x": -0.17737410962581635,
                "y": 1.0045626163482666,
                "z": 0.47309038043022156
            },
            {
                "x": 0.18099889159202576,
                "y": 1.008817434310913,
                "z": 0.47308892011642456
            },
            {
                "x": 0.17106591165065765,
                "y": 0.5919831395149231,
                "z": 0.4730895161628723
            },
            {
                "x": -0.17273925244808197,
                "y": 0.5780029296875,
                "z": 0.4730893075466156
            },
            {
                "x": 0.1752769649028778,
                "y": 0.20902684330940247,
                "z": 0.4730892777442932
            },
            {
                "x": -0.18031492829322815,
                "y": 0.20690900087356567,
                "z": 0.4730876088142395
            },
            {
                "x": 0.18165987730026245,
                "y": 0.20033997297286987,
                "z": -0.4733772873878479
            },
            {
                "x": -0.17170123755931854,
                "y": 0.21212810277938843,
                "z": -0.4733791947364807
            },
            {
                "x": 0.1702507734298706,
                "y": 0.558048665523529,
                "z": -0.4733777642250061
            },
            {
                "x": -0.1780988872051239,
                "y": 0.5678866505622864,
                "z": -0.4733792841434479
            },
            {
                "x": 0.17671309411525726,
                "y": 1.0124404430389404,
                "z": -0.4733796715736389
            },
            {
                "x": -0.17419706284999847,
                "y": 0.9986633658409119,
                "z": -0.4733791649341583
            },
            {
                "x": -0.17738457024097443,
                "y": 1.180309772491455,
                "z": -0.054380740970373154
            },
            {
                "x": -0.17790313065052032,
                "y": 0.7969714403152466,
                "z": -0.012365326285362244
            },
            {
                "x": -0.1779211312532425,
                "y": 0.3967873454093933,
                "z": -0.007543210871517658
            },
            {
                "x": 0.17936904728412628,
                "y": 0.3968244791030884,
                "z": 0.02620852179825306
            },
            {
                "x": 0.17935426533222198,
                "y": 0.7932231426239014,
                "z": 0.021726932376623154
            },
            {
                "x": 0.17936904728412628,
                "y": 1.187669277191162,
                "z": 0.027799217030405998
            }
        ]
    },
    {
        "$type": "set_kinematic_state",
        "id": 6767665,
        "is_kinematic": true
    },
    {
        "$type": "scale_object",
        "id": 6767665,
        "scale_factor": {
            "x": 1.0,
            "y": 0.8,
            "z": 1.2
        }
    },
    {
        "$type": "add_object",
        "name": "b01_tent",
        "url": "file://local_asset/Linux/b01_tent",
        "scale_factor": 1.0,
        "position": {
            "x": 10.0,
            "y": 0.0,
            "z": 4.0
        },
        "rotation": {
            "x": 0.0,
            "y": 90.0,
            "z": 0.0
        },
        "category": "tent",
        "id": 12643324,
        "affordance_points": []
    },
    {
        "$type": "set_kinematic_state",
        "id": 12643324,
        "is_kinematic": true
    },
    {
        "$type": "scale_object",
        "id": 12643324,
        "scale_factor": {
            "x": 0.4,
            "y": 1.0,
            "z": 0.8
        }
    },
    {
        "$type": "add_object",
        "name": "4ft_wood_shelving",
        "url": "file://local_asset/Linux/4ft_wood_shelving",
        "scale_factor": 1,
        "position": {
            "x": 9.3,
            "y": 0.0,
            "z": 3.5
        },
        "rotation": {
            "x": 0.0,
            "y": 90.0,
            "z": 0.0
        },
        "category": "shelf",
        "id": 894334,
        "affordance_points": [
            {
                "x": -0.17737410962581635,
                "y": 1.0045626163482666,
                "z": 0.47309038043022156
            },
            {
                "x": 0.18099889159202576,
                "y": 1.008817434310913,
                "z": 0.47308892011642456
            },
            {
                "x": 0.17106591165065765,
                "y": 0.5919831395149231,
                "z": 0.4730895161628723
            },
            {
                "x": -0.17273925244808197,
                "y": 0.5780029296875,
                "z": 0.4730893075466156
            },
            {
                "x": 0.1752769649028778,
                "y": 0.20902684330940247,
                "z": 0.4730892777442932
            },
            {
                "x": -0.18031492829322815,
                "y": 0.20690900087356567,
                "z": 0.4730876088142395
            },
            {
                "x": 0.18165987730026245,
                "y": 0.20033997297286987,
                "z": -0.4733772873878479
            },
            {
                "x": -0.17170123755931854,
                "y": 0.21212810277938843,
                "z": -0.4733791947364807
            },
            {
                "x": 0.1702507734298706,
                "y": 0.558048665523529,
                "z": -0.4733777642250061
            },
            {
                "x": -0.1780988872051239,
                "y": 0.5678866505622864,
                "z": -0.4733792841434479
            },
            {
                "x": 0.17671309411525726,
                "y": 1.0124404430389404,
                "z": -0.4733796715736389
            },
            {
                "x": -0.17419706284999847,
                "y": 0.9986633658409119,
                "z": -0.4733791649341583
            },
            {
                "x": -0.17738457024097443,
                "y": 1.180309772491455,
                "z": -0.054380740970373154
            },
            {
                "x": -0.17790313065052032,
                "y": 0.7969714403152466,
                "z": -0.012365326285362244
            },
            {
                "x": -0.1779211312532425,
                "y": 0.3967873454093933,
                "z": -0.007543210871517658
            },
            {
                "x": 0.17936904728412628,
                "y": 0.3968244791030884,
                "z": 0.02620852179825306
            },
            {
                "x": 0.17935426533222198,
                "y": 0.7932231426239014,
                "z": 0.021726932376623154
            },
            {
                "x": 0.17936904728412628,
                "y": 1.187669277191162,
                "z": 0.027799217030405998
            }
        ]
    },
    {
        "$type": "set_kinematic_state",
        "id": 894334,
        "is_kinematic": true
    },
    {
        "$type": "scale_object",
        "id": 894334,
        "scale_factor": {
            "x": 1.0,
            "y": 0.8,
            "z": 1.2
        }
    },
    {
        "$type": "add_object",
        "name": "4ft_wood_shelving",
        "url": "file://local_asset/Linux/4ft_wood_shelving",
        "scale_factor": 1,
        "position": {
            "x": 10.7,
            "y": 0.0,
            "z": 3.5
        },
        "rotation": {
            "x": 0.0,
            "y": 90.0,
            "z": 0.0
        },
        "category": "shelf",
        "id": 7980631,
        "affordance_points": [
            {
                "x": -0.17737410962581635,
                "y": 1.0045626163482666,
                "z": 0.47309038043022156
            },
            {
                "x": 0.18099889159202576,
                "y": 1.008817434310913,
                "z": 0.47308892011642456
            },
            {
                "x": 0.17106591165065765,
                "y": 0.5919831395149231,
                "z": 0.4730895161628723
            },
            {
                "x": -0.17273925244808197,
                "y": 0.5780029296875,
                "z": 0.4730893075466156
            },
            {
                "x": 0.1752769649028778,
                "y": 0.20902684330940247,
                "z": 0.4730892777442932
            },
            {
                "x": -0.18031492829322815,
                "y": 0.20690900087356567,
                "z": 0.4730876088142395
            },
            {
                "x": 0.18165987730026245,
                "y": 0.20033997297286987,
                "z": -0.4733772873878479
            },
            {
                "x": -0.17170123755931854,
                "y": 0.21212810277938843,
                "z": -0.4733791947364807
            },
            {
                "x": 0.1702507734298706,
                "y": 0.558048665523529,
                "z": -0.4733777642250061
            },
            {
                "x": -0.1780988872051239,
                "y": 0.5678866505622864,
                "z": -0.4733792841434479
            },
            {
                "x": 0.17671309411525726,
                "y": 1.0124404430389404,
                "z": -0.4733796715736389
            },
            {
                "x": -0.17419706284999847,
                "y": 0.9986633658409119,
                "z": -0.4733791649341583
            },
            {
                "x": -0.17738457024097443,
                "y": 1.180309772491455,
                "z": -0.054380740970373154
            },
            {
                "x": -0.17790313065052032,
                "y": 0.7969714403152466,
                "z": -0.012365326285362244
            },
            {
                "x": -0.1779211312532425,
                "y": 0.3967873454093933,
                "z": -0.007543210871517658
            },
            {
                "x": 0.17936904728412628,
                "y": 0.3968244791030884,
                "z": 0.02620852179825306
            },
            {
                "x": 0.17935426533222198,
                "y": 0.7932231426239014,
                "z": 0.021726932376623154
            },
            {
                "x": 0.17936904728412628,
                "y": 1.187669277191162,
                "z": 0.027799217030405998
            }
        ]
    },
    {
        "$type": "set_kinematic_state",
        "id": 7980631,
        "is_kinematic": true
    },
    {
        "$type": "scale_object",
        "id": 7980631,
        "scale_factor": {
            "x": 1.0,
            "y": 0.8,
            "z": 1.2
        }
    },
    {
        "$type": "add_object",
        "name": "b01_tent",
        "url": "file://local_asset/Linux/b01_tent",
        "scale_factor": 1.0,
        "position": {
            "x": 15.0,
            "y": 0.0,
            "z": -2.5
        },
        "rotation": {
            "x": 0.0,
            "y": 90.0,
            "z": 0.0
        },
        "category": "tent",
        "id": 12133844,
        "affordance_points": []
    },
    {
        "$type": "set_kinematic_state",
        "id": 12133844,
        "is_kinematic": true
    },
    {
        "$type": "scale_object",
        "id": 12133844,
        "scale_factor": {
            "x": 0.4,
            "y": 1.0,
            "z": 0.8
        }
    },
    {
        "$type": "add_object",
        "name": "4ft_wood_shelving",
        "url": "file://local_asset/Linux/4ft_wood_shelving",
        "scale_factor": 1,
        "position": {
            "x": 14.3,
            "y": 0.0,
            "z": -2.0
        },
        "rotation": {
            "x": 0.0,
            "y": 90.0,
            "z": 0.0
        },
        "category": "shelf",
        "id": 15762228,
        "affordance_points": [
            {
                "x": -0.17737410962581635,
                "y": 1.0045626163482666,
                "z": 0.47309038043022156
            },
            {
                "x": 0.18099889159202576,
                "y": 1.008817434310913,
                "z": 0.47308892011642456
            },
            {
                "x": 0.17106591165065765,
                "y": 0.5919831395149231,
                "z": 0.4730895161628723
            },
            {
                "x": -0.17273925244808197,
                "y": 0.5780029296875,
                "z": 0.4730893075466156
            },
            {
                "x": 0.1752769649028778,
                "y": 0.20902684330940247,
                "z": 0.4730892777442932
            },
            {
                "x": -0.18031492829322815,
                "y": 0.20690900087356567,
                "z": 0.4730876088142395
            },
            {
                "x": 0.18165987730026245,
                "y": 0.20033997297286987,
                "z": -0.4733772873878479
            },
            {
                "x": -0.17170123755931854,
                "y": 0.21212810277938843,
                "z": -0.4733791947364807
            },
            {
                "x": 0.1702507734298706,
                "y": 0.558048665523529,
                "z": -0.4733777642250061
            },
            {
                "x": -0.1780988872051239,
                "y": 0.5678866505622864,
                "z": -0.4733792841434479
            },
            {
                "x": 0.17671309411525726,
                "y": 1.0124404430389404,
                "z": -0.4733796715736389
            },
            {
                "x": -0.17419706284999847,
                "y": 0.9986633658409119,
                "z": -0.4733791649341583
            },
            {
                "x": -0.17738457024097443,
                "y": 1.180309772491455,
                "z": -0.054380740970373154
            },
            {
                "x": -0.17790313065052032,
                "y": 0.7969714403152466,
                "z": -0.012365326285362244
            },
            {
                "x": -0.1779211312532425,
                "y": 0.3967873454093933,
                "z": -0.007543210871517658
            },
            {
                "x": 0.17936904728412628,
                "y": 0.3968244791030884,
                "z": 0.02620852179825306
            },
            {
                "x": 0.17935426533222198,
                "y": 0.7932231426239014,
                "z": 0.021726932376623154
            },
            {
                "x": 0.17936904728412628,
                "y": 1.187669277191162,
                "z": 0.027799217030405998
            }
        ]
    },
    {
        "$type": "set_kinematic_state",
        "id": 15762228,
        "is_kinematic": true
    },
    {
        "$type": "scale_object",
        "id": 15762228,
        "scale_factor": {
            "x": 1.0,
            "y": 0.8,
            "z": 1.2
        }
    },
    {
        "$type": "add_object",
        "name": "4ft_wood_shelving",
        "url": "file://local_asset/Linux/4ft_wood_shelving",
        "scale_factor": 1,
        "position": {
            "x": 15.7,
            "y": 0.0,
            "z": -2.0
        },
        "rotation": {
            "x": 0.0,
            "y": 90.0,
            "z": 0.0
        },
        "category": "shelf",
        "id": 15727027,
        "affordance_points": [
            {
                "x": -0.17737410962581635,
                "y": 1.0045626163482666,
                "z": 0.47309038043022156
            },
            {
                "x": 0.18099889159202576,
                "y": 1.008817434310913,
                "z": 0.47308892011642456
            },
            {
                "x": 0.17106591165065765,
                "y": 0.5919831395149231,
                "z": 0.4730895161628723
            },
            {
                "x": -0.17273925244808197,
                "y": 0.5780029296875,
                "z": 0.4730893075466156
            },
            {
                "x": 0.1752769649028778,
                "y": 0.20902684330940247,
                "z": 0.4730892777442932
            },
            {
                "x": -0.18031492829322815,
                "y": 0.20690900087356567,
                "z": 0.4730876088142395
            },
            {
                "x": 0.18165987730026245,
                "y": 0.20033997297286987,
                "z": -0.4733772873878479
            },
            {
                "x": -0.17170123755931854,
                "y": 0.21212810277938843,
                "z": -0.4733791947364807
            },
            {
                "x": 0.1702507734298706,
                "y": 0.558048665523529,
                "z": -0.4733777642250061
            },
            {
                "x": -0.1780988872051239,
                "y": 0.5678866505622864,
                "z": -0.4733792841434479
            },
            {
                "x": 0.17671309411525726,
                "y": 1.0124404430389404,
                "z": -0.4733796715736389
            },
            {
                "x": -0.17419706284999847,
                "y": 0.9986633658409119,
                "z": -0.4733791649341583
            },
            {
                "x": -0.17738457024097443,
                "y": 1.180309772491455,
                "z": -0.054380740970373154
            },
            {
                "x": -0.17790313065052032,
                "y": 0.7969714403152466,
                "z": -0.012365326285362244
            },
            {
                "x": -0.1779211312532425,
                "y": 0.3967873454093933,
                "z": -0.007543210871517658
            },
            {
                "x": 0.17936904728412628,
                "y": 0.3968244791030884,
                "z": 0.02620852179825306
            },
            {
                "x": 0.17935426533222198,
                "y": 0.7932231426239014,
                "z": 0.021726932376623154
            },
            {
                "x": 0.17936904728412628,
                "y": 1.187669277191162,
                "z": 0.027799217030405998
            }
        ]
    },
    {
        "$type": "set_kinematic_state",
        "id": 15727027,
        "is_kinematic": true
    },
    {
        "$type": "scale_object",
        "id": 15727027,
        "scale_factor": {
            "x": 1.0,
            "y": 0.8,
            "z": 1.2
        }
    },
    {
        "$type": "add_object",
        "name": "b01_tent",
        "url": "file://local_asset/Linux/b01_tent",
        "scale_factor": 1.0,
        "position": {
            "x": 15.0,
            "y": 0.0,
            "z": 4.0
        },
        "rotation": {
            "x": 0.0,
            "y": 90.0,
            "z": 0.0
        },
        "category": "tent",
        "id": 6671742,
        "affordance_points": []
    },
    {
        "$type": "set_kinematic_state",
        "id": 6671742,
        "is_kinematic": true
    },
    {
        "$type": "scale_object",
        "id": 6671742,
        "scale_factor": {
            "x": 0.4,
            "y": 1.0,
            "z": 0.8
        }
    },
    {
        "$type": "add_object",
        "name": "4ft_wood_shelving",
        "url": "file://local_asset/Linux/4ft_wood_shelving",
        "scale_factor": 1,
        "position": {
            "x": 14.3,
            "y": 0.0,
            "z": 3.5
        },
        "rotation": {
            "x": 0.0,
            "y": 90.0,
            "z": 0.0
        },
        "category": "shelf",
        "id": 10635107,
        "affordance_points": [
            {
                "x": -0.17737410962581635,
                "y": 1.0045626163482666,
                "z": 0.47309038043022156
            },
            {
                "x": 0.18099889159202576,
                "y": 1.008817434310913,
                "z": 0.47308892011642456
            },
            {
                "x": 0.17106591165065765,
                "y": 0.5919831395149231,
                "z": 0.4730895161628723
            },
            {
                "x": -0.17273925244808197,
                "y": 0.5780029296875,
                "z": 0.4730893075466156
            },
            {
                "x": 0.1752769649028778,
                "y": 0.20902684330940247,
                "z": 0.4730892777442932
            },
            {
                "x": -0.18031492829322815,
                "y": 0.20690900087356567,
                "z": 0.4730876088142395
            },
            {
                "x": 0.18165987730026245,
                "y": 0.20033997297286987,
                "z": -0.4733772873878479
            },
            {
                "x": -0.17170123755931854,
                "y": 0.21212810277938843,
                "z": -0.4733791947364807
            },
            {
                "x": 0.1702507734298706,
                "y": 0.558048665523529,
                "z": -0.4733777642250061
            },
            {
                "x": -0.1780988872051239,
                "y": 0.5678866505622864,
                "z": -0.4733792841434479
            },
            {
                "x": 0.17671309411525726,
                "y": 1.0124404430389404,
                "z": -0.4733796715736389
            },
            {
                "x": -0.17419706284999847,
                "y": 0.9986633658409119,
                "z": -0.4733791649341583
            },
            {
                "x": -0.17738457024097443,
                "y": 1.180309772491455,
                "z": -0.054380740970373154
            },
            {
                "x": -0.17790313065052032,
                "y": 0.7969714403152466,
                "z": -0.012365326285362244
            },
            {
                "x": -0.1779211312532425,
                "y": 0.3967873454093933,
                "z": -0.007543210871517658
            },
            {
                "x": 0.17936904728412628,
                "y": 0.3968244791030884,
                "z": 0.02620852179825306
            },
            {
                "x": 0.17935426533222198,
                "y": 0.7932231426239014,
                "z": 0.021726932376623154
            },
            {
                "x": 0.17936904728412628,
                "y": 1.187669277191162,
                "z": 0.027799217030405998
            }
        ]
    },
    {
        "$type": "set_kinematic_state",
        "id": 10635107,
        "is_kinematic": true
    },
    {
        "$type": "scale_object",
        "id": 10635107,
        "scale_factor": {
            "x": 1.0,
            "y": 0.8,
            "z": 1.2
        }
    },
    {
        "$type": "add_object",
        "name": "4ft_wood_shelving",
        "url": "file://local_asset/Linux/4ft_wood_shelving",
        "scale_factor": 1,
        "position": {
            "x": 15.7,
            "y": 0.0,
            "z": 3.5
        },
        "rotation": {
            "x": 0.0,
            "y": 90.0,
            "z": 0.0
        },
        "category": "shelf",
        "id": 573310,
        "affordance_points": [
            {
                "x": -0.17737410962581635,
                "y": 1.0045626163482666,
                "z": 0.47309038043022156
            },
            {
                "x": 0.18099889159202576,
                "y": 1.008817434310913,
                "z": 0.47308892011642456
            },
            {
                "x": 0.17106591165065765,
                "y": 0.5919831395149231,
                "z": 0.4730895161628723
            },
            {
                "x": -0.17273925244808197,
                "y": 0.5780029296875,
                "z": 0.4730893075466156
            },
            {
                "x": 0.1752769649028778,
                "y": 0.20902684330940247,
                "z": 0.4730892777442932
            },
            {
                "x": -0.18031492829322815,
                "y": 0.20690900087356567,
                "z": 0.4730876088142395
            },
            {
                "x": 0.18165987730026245,
                "y": 0.20033997297286987,
                "z": -0.4733772873878479
            },
            {
                "x": -0.17170123755931854,
                "y": 0.21212810277938843,
                "z": -0.4733791947364807
            },
            {
                "x": 0.1702507734298706,
                "y": 0.558048665523529,
                "z": -0.4733777642250061
            },
            {
                "x": -0.1780988872051239,
                "y": 0.5678866505622864,
                "z": -0.4733792841434479
            },
            {
                "x": 0.17671309411525726,
                "y": 1.0124404430389404,
                "z": -0.4733796715736389
            },
            {
                "x": -0.17419706284999847,
                "y": 0.9986633658409119,
                "z": -0.4733791649341583
            },
            {
                "x": -0.17738457024097443,
                "y": 1.180309772491455,
                "z": -0.054380740970373154
            },
            {
                "x": -0.17790313065052032,
                "y": 0.7969714403152466,
                "z": -0.012365326285362244
            },
            {
                "x": -0.1779211312532425,
                "y": 0.3967873454093933,
                "z": -0.007543210871517658
            },
            {
                "x": 0.17936904728412628,
                "y": 0.3968244791030884,
                "z": 0.02620852179825306
            },
            {
                "x": 0.17935426533222198,
                "y": 0.7932231426239014,
                "z": 0.021726932376623154
            },
            {
                "x": 0.17936904728412628,
                "y": 1.187669277191162,
                "z": 0.027799217030405998
            }
        ]
    },
    {
        "$type": "set_kinematic_state",
        "id": 573310,
        "is_kinematic": true
    },
    {
        "$type": "scale_object",
        "id": 573310,
        "scale_factor": {
            "x": 1.0,
            "y": 0.8,
            "z": 1.2
        }
    },
    {
        "$type": "add_object",
        "name": "b01_tent",
        "url": "file://local_asset/Linux/b01_tent",
        "scale_factor": 1.0,
        "position": {
            "x": 20.0,
            "y": 0.0,
            "z": -2.5
        },
        "rotation": {
            "x": 0.0,
            "y": 90.0,
            "z": 0.0
        },
        "category": "tent",
        "id": 7158878,
        "affordance_points": []
    },
    {
        "$type": "set_kinematic_state",
        "id": 7158878,
        "is_kinematic": true
    },
    {
        "$type": "scale_object",
        "id": 7158878,
        "scale_factor": {
            "x": 0.4,
            "y": 1.0,
            "z": 0.8
        }
    },
    {
        "$type": "add_object",
        "name": "4ft_wood_shelving",
        "url": "file://local_asset/Linux/4ft_wood_shelving",
        "scale_factor": 1,
        "position": {
            "x": 19.3,
            "y": 0.0,
            "z": -2.0
        },
        "rotation": {
            "x": 0.0,
            "y": 90.0,
            "z": 0.0
        },
        "category": "shelf",
        "id": 12361271,
        "affordance_points": [
            {
                "x": -0.17737410962581635,
                "y": 1.0045626163482666,
                "z": 0.47309038043022156
            },
            {
                "x": 0.18099889159202576,
                "y": 1.008817434310913,
                "z": 0.47308892011642456
            },
            {
                "x": 0.17106591165065765,
                "y": 0.5919831395149231,
                "z": 0.4730895161628723
            },
            {
                "x": -0.17273925244808197,
                "y": 0.5780029296875,
                "z": 0.4730893075466156
            },
            {
                "x": 0.1752769649028778,
                "y": 0.20902684330940247,
                "z": 0.4730892777442932
            },
            {
                "x": -0.18031492829322815,
                "y": 0.20690900087356567,
                "z": 0.4730876088142395
            },
            {
                "x": 0.18165987730026245,
                "y": 0.20033997297286987,
                "z": -0.4733772873878479
            },
            {
                "x": -0.17170123755931854,
                "y": 0.21212810277938843,
                "z": -0.4733791947364807
            },
            {
                "x": 0.1702507734298706,
                "y": 0.558048665523529,
                "z": -0.4733777642250061
            },
            {
                "x": -0.1780988872051239,
                "y": 0.5678866505622864,
                "z": -0.4733792841434479
            },
            {
                "x": 0.17671309411525726,
                "y": 1.0124404430389404,
                "z": -0.4733796715736389
            },
            {
                "x": -0.17419706284999847,
                "y": 0.9986633658409119,
                "z": -0.4733791649341583
            },
            {
                "x": -0.17738457024097443,
                "y": 1.180309772491455,
                "z": -0.054380740970373154
            },
            {
                "x": -0.17790313065052032,
                "y": 0.7969714403152466,
                "z": -0.012365326285362244
            },
            {
                "x": -0.1779211312532425,
                "y": 0.3967873454093933,
                "z": -0.007543210871517658
            },
            {
                "x": 0.17936904728412628,
                "y": 0.3968244791030884,
                "z": 0.02620852179825306
            },
            {
                "x": 0.17935426533222198,
                "y": 0.7932231426239014,
                "z": 0.021726932376623154
            },
            {
                "x": 0.17936904728412628,
                "y": 1.187669277191162,
                "z": 0.027799217030405998
            }
        ]
    },
    {
        "$type": "set_kinematic_state",
        "id": 12361271,
        "is_kinematic": true
    },
    {
        "$type": "scale_object",
        "id": 12361271,
        "scale_factor": {
            "x": 1.0,
            "y": 0.8,
            "z": 1.2
        }
    },
    {
        "$type": "add_object",
        "name": "4ft_wood_shelving",
        "url": "file://local_asset/Linux/4ft_wood_shelving",
        "scale_factor": 1,
        "position": {
            "x": 20.7,
            "y": 0.0,
            "z": -2.0
        },
        "rotation": {
            "x": 0.0,
            "y": 90.0,
            "z": 0.0
        },
        "category": "shelf",
        "id": 4755625,
        "affordance_points": [
            {
                "x": -0.17737410962581635,
                "y": 1.0045626163482666,
                "z": 0.47309038043022156
            },
            {
                "x": 0.18099889159202576,
                "y": 1.008817434310913,
                "z": 0.47308892011642456
            },
            {
                "x": 0.17106591165065765,
                "y": 0.5919831395149231,
                "z": 0.4730895161628723
            },
            {
                "x": -0.17273925244808197,
                "y": 0.5780029296875,
                "z": 0.4730893075466156
            },
            {
                "x": 0.1752769649028778,
                "y": 0.20902684330940247,
                "z": 0.4730892777442932
            },
            {
                "x": -0.18031492829322815,
                "y": 0.20690900087356567,
                "z": 0.4730876088142395
            },
            {
                "x": 0.18165987730026245,
                "y": 0.20033997297286987,
                "z": -0.4733772873878479
            },
            {
                "x": -0.17170123755931854,
                "y": 0.21212810277938843,
                "z": -0.4733791947364807
            },
            {
                "x": 0.1702507734298706,
                "y": 0.558048665523529,
                "z": -0.4733777642250061
            },
            {
                "x": -0.1780988872051239,
                "y": 0.5678866505622864,
                "z": -0.4733792841434479
            },
            {
                "x": 0.17671309411525726,
                "y": 1.0124404430389404,
                "z": -0.4733796715736389
            },
            {
                "x": -0.17419706284999847,
                "y": 0.9986633658409119,
                "z": -0.4733791649341583
            },
            {
                "x": -0.17738457024097443,
                "y": 1.180309772491455,
                "z": -0.054380740970373154
            },
            {
                "x": -0.17790313065052032,
                "y": 0.7969714403152466,
                "z": -0.012365326285362244
            },
            {
                "x": -0.1779211312532425,
                "y": 0.3967873454093933,
                "z": -0.007543210871517658
            },
            {
                "x": 0.17936904728412628,
                "y": 0.3968244791030884,
                "z": 0.02620852179825306
            },
            {
                "x": 0.17935426533222198,
                "y": 0.7932231426239014,
                "z": 0.021726932376623154
            },
            {
                "x": 0.17936904728412628,
                "y": 1.187669277191162,
                "z": 0.027799217030405998
            }
        ]
    },
    {
        "$type": "set_kinematic_state",
        "id": 4755625,
        "is_kinematic": true
    },
    {
        "$type": "scale_object",
        "id": 4755625,
        "scale_factor": {
            "x": 1.0,
            "y": 0.8,
            "z": 1.2
        }
    },
    {
        "$type": "add_object",
        "name": "b01_tent",
        "url": "file://local_asset/Linux/b01_tent",
        "scale_factor": 1.0,
        "position": {
            "x": 20.0,
            "y": 0.0,
            "z": 4.0
        },
        "rotation": {
            "x": 0.0,
            "y": 90.0,
            "z": 0.0
        },
        "category": "tent",
        "id": 15858248,
        "affordance_points": []
    },
    {
        "$type": "set_kinematic_state",
        "id": 15858248,
        "is_kinematic": true
    },
    {
        "$type": "scale_object",
        "id": 15858248,
        "scale_factor": {
            "x": 0.4,
            "y": 1.0,
            "z": 0.8
        }
    },
    {
        "$type": "add_object",
        "name": "4ft_wood_shelving",
        "url": "file://local_asset/Linux/4ft_wood_shelving",
        "scale_factor": 1,
        "position": {
            "x": 19.3,
            "y": 0.0,
            "z": 3.5
        },
        "rotation": {
            "x": 0.0,
            "y": 90.0,
            "z": 0.0
        },
        "category": "shelf",
        "id": 13537760,
        "affordance_points": [
            {
                "x": -0.17737410962581635,
                "y": 1.0045626163482666,
                "z": 0.47309038043022156
            },
            {
                "x": 0.18099889159202576,
                "y": 1.008817434310913,
                "z": 0.47308892011642456
            },
            {
                "x": 0.17106591165065765,
                "y": 0.5919831395149231,
                "z": 0.4730895161628723
            },
            {
                "x": -0.17273925244808197,
                "y": 0.5780029296875,
                "z": 0.4730893075466156
            },
            {
                "x": 0.1752769649028778,
                "y": 0.20902684330940247,
                "z": 0.4730892777442932
            },
            {
                "x": -0.18031492829322815,
                "y": 0.20690900087356567,
                "z": 0.4730876088142395
            },
            {
                "x": 0.18165987730026245,
                "y": 0.20033997297286987,
                "z": -0.4733772873878479
            },
            {
                "x": -0.17170123755931854,
                "y": 0.21212810277938843,
                "z": -0.4733791947364807
            },
            {
                "x": 0.1702507734298706,
                "y": 0.558048665523529,
                "z": -0.4733777642250061
            },
            {
                "x": -0.1780988872051239,
                "y": 0.5678866505622864,
                "z": -0.4733792841434479
            },
            {
                "x": 0.17671309411525726,
                "y": 1.0124404430389404,
                "z": -0.4733796715736389
            },
            {
                "x": -0.17419706284999847,
                "y": 0.9986633658409119,
                "z": -0.4733791649341583
            },
            {
                "x": -0.17738457024097443,
                "y": 1.180309772491455,
                "z": -0.054380740970373154
            },
            {
                "x": -0.17790313065052032,
                "y": 0.7969714403152466,
                "z": -0.012365326285362244
            },
            {
                "x": -0.1779211312532425,
                "y": 0.3967873454093933,
                "z": -0.007543210871517658
            },
            {
                "x": 0.17936904728412628,
                "y": 0.3968244791030884,
                "z": 0.02620852179825306
            },
            {
                "x": 0.17935426533222198,
                "y": 0.7932231426239014,
                "z": 0.021726932376623154
            },
            {
                "x": 0.17936904728412628,
                "y": 1.187669277191162,
                "z": 0.027799217030405998
            }
        ]
    },
    {
        "$type": "set_kinematic_state",
        "id": 13537760,
        "is_kinematic": true
    },
    {
        "$type": "scale_object",
        "id": 13537760,
        "scale_factor": {
            "x": 1.0,
            "y": 0.8,
            "z": 1.2
        }
    },
    {
        "$type": "add_object",
        "name": "4ft_wood_shelving",
        "url": "file://local_asset/Linux/4ft_wood_shelving",
        "scale_factor": 1,
        "position": {
            "x": 20.7,
            "y": 0.0,
            "z": 3.5
        },
        "rotation": {
            "x": 0.0,
            "y": 90.0,
            "z": 0.0
        },
        "category": "shelf",
        "id": 11670610,
        "affordance_points": [
            {
                "x": -0.17737410962581635,
                "y": 1.0045626163482666,
                "z": 0.47309038043022156
            },
            {
                "x": 0.18099889159202576,
                "y": 1.008817434310913,
                "z": 0.47308892011642456
            },
            {
                "x": 0.17106591165065765,
                "y": 0.5919831395149231,
                "z": 0.4730895161628723
            },
            {
                "x": -0.17273925244808197,
                "y": 0.5780029296875,
                "z": 0.4730893075466156
            },
            {
                "x": 0.1752769649028778,
                "y": 0.20902684330940247,
                "z": 0.4730892777442932
            },
            {
                "x": -0.18031492829322815,
                "y": 0.20690900087356567,
                "z": 0.4730876088142395
            },
            {
                "x": 0.18165987730026245,
                "y": 0.20033997297286987,
                "z": -0.4733772873878479
            },
            {
                "x": -0.17170123755931854,
                "y": 0.21212810277938843,
                "z": -0.4733791947364807
            },
            {
                "x": 0.1702507734298706,
                "y": 0.558048665523529,
                "z": -0.4733777642250061
            },
            {
                "x": -0.1780988872051239,
                "y": 0.5678866505622864,
                "z": -0.4733792841434479
            },
            {
                "x": 0.17671309411525726,
                "y": 1.0124404430389404,
                "z": -0.4733796715736389
            },
            {
                "x": -0.17419706284999847,
                "y": 0.9986633658409119,
                "z": -0.4733791649341583
            },
            {
                "x": -0.17738457024097443,
                "y": 1.180309772491455,
                "z": -0.054380740970373154
            },
            {
                "x": -0.17790313065052032,
                "y": 0.7969714403152466,
                "z": -0.012365326285362244
            },
            {
                "x": -0.1779211312532425,
                "y": 0.3967873454093933,
                "z": -0.007543210871517658
            },
            {
                "x": 0.17936904728412628,
                "y": 0.3968244791030884,
                "z": 0.02620852179825306
            },
            {
                "x": 0.17935426533222198,
                "y": 0.7932231426239014,
                "z": 0.021726932376623154
            },
            {
                "x": 0.17936904728412628,
                "y": 1.187669277191162,
                "z": 0.027799217030405998
            }
        ]
    },
    {
        "$type": "set_kinematic_state",
        "id": 11670610,
        "is_kinematic": true
    },
    {
        "$type": "scale_object",
        "id": 11670610,
        "scale_factor": {
            "x": 1.0,
            "y": 0.8,
            "z": 1.2
        }
    },
    {
        "$type": "add_object",
        "name": "basket_18inx18inx12iin_plastic_lattice",
        "url": "file://local_asset/Linux/basket_18inx18inx12iin_plastic_lattice",
        "scale_factor": 1,
        "position": {
            "x": 14.3,
            "y": 0.99,
            "z": 3.5
        },
        "rotation": {
            "x": 0.0,
            "y": 99.53217979917133,
            "z": 0.0
        },
        "category": "basket",
        "id": 13436726,
        "affordance_points": [
            {
                "x": -0.2285,
                "y": 0.305,
                "z": 0.0
            },
            {
                "x": 0.2285,
                "y": 0.305,
                "z": 0.0
            },
            {
                "x": 0,
                "y": 0.305,
                "z": 0.2285
            },
            {
                "x": 0,
                "y": 0.305,
                "z": -0.2285
            }
        ]
    },
    {
        "$type": "set_mass",
        "id": 13436726,
        "mass": 10
    },
    {
        "$type": "scale_object",
        "id": 13436726,
        "scale_factor": {
            "x": 1.0,
            "y": 1.0,
            "z": 1.0
        }
    },
    {
        "$type": "add_object",
        "name": "basket_18inx18inx12iin_wicker",
        "url": "file://local_asset/Linux/basket_18inx18inx12iin_wicker",
        "scale_factor": 1,
        "position": {
            "x": 9.3,
            "y": 0.99,
            "z": 3.5
        },
        "rotation": {
            "x": 0.0,
            "y": 251.75429352193737,
            "z": 0.0
        },
        "category": "basket",
        "id": 6973461,
        "affordance_points": [
            {
                "x": -0.2285,
                "y": 0.305,
                "z": 0.0
            },
            {
                "x": 0.2285,
                "y": 0.305,
                "z": 0.0
            },
            {
                "x": 0,
                "y": 0.305,
                "z": 0.2285
            },
            {
                "x": 0,
                "y": 0.305,
                "z": -0.2285
            }
        ]
    },
    {
        "$type": "set_mass",
        "id": 6973461,
        "mass": 10
    },
    {
        "$type": "scale_object",
        "id": 6973461,
        "scale_factor": {
            "x": 1.0,
            "y": 1.0,
            "z": 1.0
        }
    },
    {
        "$type": "add_object",
        "name": "basket_18inx18inx12iin_bamboo",
        "url": "file://local_asset/Linux/basket_18inx18inx12iin_bamboo",
        "scale_factor": 1,
        "position": {
            "x": 14.3,
            "y": 0.99,
            "z": -2.0
        },
        "rotation": {
            "x": 0.0,
            "y": 279.3728594031556,
            "z": 0.0
        },
        "category": "basket",
        "id": 12740474,
        "affordance_points": [
            {
                "x": -0.2285,
                "y": 0.305,
                "z": 0.0
            },
            {
                "x": 0.2285,
                "y": 0.305,
                "z": 0.0
            },
            {
                "x": 0,
                "y": 0.305,
                "z": 0.2285
            },
            {
                "x": 0,
                "y": 0.305,
                "z": -0.2285
            }
        ]
    },
    {
        "$type": "set_mass",
        "id": 12740474,
        "mass": 10
    },
    {
        "$type": "scale_object",
        "id": 12740474,
        "scale_factor": {
            "x": 1.0,
            "y": 1.0,
            "z": 1.0
        }
    },
    {
        "$type": "add_object",
        "name": "apple",
        "url": "file://local_asset/Linux/apple",
        "scale_factor": 0.08862933,
        "position": {
            "x": 8.9,
            "y": 0.66,
            "z": -2.0
        },
        "rotation": {
            "x": 0.0,
            "y": 173.86781767026105,
            "z": 0.0
        },
        "category": "apple",
        "id": 8391431,
        "affordance_points": []
    },
    {
        "$type": "set_mass",
        "id": 8391431,
        "mass": 10
    },
    {
        "$type": "scale_object",
        "id": 8391431,
        "scale_factor": {
            "x": 1.5,
            "y": 1.5,
            "z": 1.5
        }
    },
    {
        "$type": "add_object",
        "name": "apple",
        "url": "file://local_asset/Linux/apple",
        "scale_factor": 0.08862933,
        "position": {
            "x": 11.1,
            "y": 0.33,
            "z": -2.0
        },
        "rotation": {
            "x": 0.0,
            "y": 43.125750483457644,
            "z": 0.0
        },
        "category": "apple",
        "id": 253324,
        "affordance_points": []
    },
    {
        "$type": "set_mass",
        "id": 253324,
        "mass": 10
    },
    {
        "$type": "scale_object",
        "id": 253324,
        "scale_factor": {
            "x": 1.5,
            "y": 1.5,
            "z": 1.5
        }
    },
    {
        "$type": "add_object",
        "name": "b04_orange_00",
        "url": "file://local_asset/Linux/b04_orange_00",
        "scale_factor": 0.1,
        "position": {
            "x": 8.9,
            "y": 0.99,
            "z": -2.0
        },
        "rotation": {
            "x": 0.0,
            "y": 309.54431084066505,
            "z": 0.0
        },
        "category": "orange",
        "id": 2695019,
        "affordance_points": []
    },
    {
        "$type": "set_mass",
        "id": 2695019,
        "mass": 10
    },
    {
        "$type": "scale_object",
        "id": 2695019,
        "scale_factor": {
            "x": 1.5,
            "y": 1.5,
            "z": 1.5
        }
    },
    {
        "$type": "add_object",
        "name": "b04_orange_00",
        "url": "file://local_asset/Linux/b04_orange_00",
        "scale_factor": 0.1,
        "position": {
            "x": 9.3,
            "y": 0.99,
            "z": -2.0
        },
        "rotation": {
            "x": 0.0,
            "y": 189.67902953531177,
            "z": 0.0
        },
        "category": "orange",
        "id": 10751190,
        "affordance_points": []
    },
    {
        "$type": "set_mass",
        "id": 10751190,
        "mass": 10
    },
    {
        "$type": "scale_object",
        "id": 10751190,
        "scale_factor": {
            "x": 1.5,
            "y": 1.5,
            "z": 1.5
        }
    },
    {
        "$type": "add_object",
        "name": "b04_orange_00",
        "url": "file://local_asset/Linux/b04_orange_00",
        "scale_factor": 0.1,
        "position": {
            "x": 9.700000000000001,
            "y": 0.66,
            "z": -2.0
        },
        "rotation": {
            "x": 0.0,
            "y": 115.9512494216496,
            "z": 0.0
        },
        "category": "orange",
        "id": 5759938,
        "affordance_points": []
    },
    {
        "$type": "set_mass",
        "id": 5759938,
        "mass": 10
    },
    {
        "$type": "scale_object",
        "id": 5759938,
        "scale_factor": {
            "x": 1.5,
            "y": 1.5,
            "z": 1.5
        }
    },
    {
        "$type": "add_object",
        "name": "b03_banan_001",
        "url": "file://local_asset/Linux/b03_banan_001",
        "scale_factor": 1.0,
        "position": {
            "x": 10.299999999999999,
            "y": 0.33,
            "z": -2.0
        },
        "rotation": {
            "x": 0.0,
            "y": 189.2024659327406,
            "z": 0.0
        },
        "category": "banana",
        "id": 7128467,
        "affordance_points": []
    },
    {
        "$type": "set_mass",
        "id": 7128467,
        "mass": 10
    },
    {
        "$type": "scale_object",
        "id": 7128467,
        "scale_factor": {
            "x": 1.0,
            "y": 1.0,
            "z": 1.0
        }
    },
    {
        "$type": "add_object",
        "name": "apple",
        "url": "file://local_asset/Linux/apple",
        "scale_factor": 0.08862933,
        "position": {
            "x": 9.700000000000001,
            "y": 0.66,
            "z": 3.5
        },
        "rotation": {
            "x": 0.0,
            "y": 87.22467069194123,
            "z": 0.0
        },
        "category": "apple",
        "id": 1182002,
        "affordance_points": []
    },
    {
        "$type": "set_mass",
        "id": 1182002,
        "mass": 10
    },
    {
        "$type": "scale_object",
        "id": 1182002,
        "scale_factor": {
            "x": 1.5,
            "y": 1.5,
            "z": 1.5
        }
    },
    {
        "$type": "add_object",
        "name": "b04_red_grapes",
        "url": "file://local_asset/Linux/b04_red_grapes",
        "scale_factor": 1.0,
        "position": {
            "x": 10.7,
            "y": 0.99,
            "z": 3.5
        },
        "rotation": {
            "x": 0.0,
            "y": 227.79662332352208,
            "z": 0.0
        },
        "category": "grape",
        "id": 14982379,
        "affordance_points": []
    },
    {
        "$type": "set_mass",
        "id": 14982379,
        "mass": 10
    },
    {
        "$type": "scale_object",
        "id": 14982379,
        "scale_factor": {
            "x": 1.2,
            "y": 1.2,
            "z": 1.2
        }
    },
    {
        "$type": "add_object",
        "name": "b04_red_grapes",
        "url": "file://local_asset/Linux/b04_red_grapes",
        "scale_factor": 1.0,
        "position": {
            "x": 10.7,
            "y": 0.66,
            "z": 3.5
        },
        "rotation": {
            "x": 0.0,
            "y": 90.62685405183268,
            "z": 0.0
        },
        "category": "grape",
        "id": 15745649,
        "affordance_points": []
    },
    {
        "$type": "set_mass",
        "id": 15745649,
        "mass": 10
    },
    {
        "$type": "scale_object",
        "id": 15745649,
        "scale_factor": {
            "x": 1.2,
            "y": 1.2,
            "z": 1.2
        }
    },
    {
        "$type": "add_object",
        "name": "b04_red_grapes",
        "url": "file://local_asset/Linux/b04_red_grapes",
        "scale_factor": 1.0,
        "position": {
            "x": 10.299999999999999,
            "y": 0.66,
            "z": 3.5
        },
        "rotation": {
            "x": 0.0,
            "y": 261.17800471265616,
            "z": 0.0
        },
        "category": "grape",
        "id": 3882552,
        "affordance_points": []
    },
    {
        "$type": "set_mass",
        "id": 3882552,
        "mass": 10
    },
    {
        "$type": "scale_object",
        "id": 3882552,
        "scale_factor": {
            "x": 1.2,
            "y": 1.2,
            "z": 1.2
        }
    },
    {
        "$type": "add_object",
        "name": "b03_banan_001",
        "url": "file://local_asset/Linux/b03_banan_001",
        "scale_factor": 1.0,
        "position": {
            "x": 8.9,
            "y": 0.66,
            "z": 3.5
        },
        "rotation": {
            "x": 0.0,
            "y": 234.4635220471825,
            "z": 0.0
        },
        "category": "banana",
        "id": 15886850,
        "affordance_points": []
    },
    {
        "$type": "set_mass",
        "id": 15886850,
        "mass": 10
    },
    {
        "$type": "scale_object",
        "id": 15886850,
        "scale_factor": {
            "x": 1.0,
            "y": 1.0,
            "z": 1.0
        }
    },
    {
        "$type": "add_object",
        "name": "b03_banan_001",
        "url": "file://local_asset/Linux/b03_banan_001",
        "scale_factor": 1.0,
        "position": {
            "x": 8.9,
            "y": 0.33,
            "z": 3.5
        },
        "rotation": {
            "x": 0.0,
            "y": 286.2719456433025,
            "z": 0.0
        },
        "category": "banana",
        "id": 2273534,
        "affordance_points": []
    },
    {
        "$type": "set_mass",
        "id": 2273534,
        "mass": 10
    },
    {
        "$type": "scale_object",
        "id": 2273534,
        "scale_factor": {
            "x": 1.0,
            "y": 1.0,
            "z": 1.0
        }
    },
    {
        "$type": "add_object",
        "name": "b03_loafbread",
        "url": "file://local_asset/Linux/b03_loafbread",
        "scale_factor": 1.0,
        "position": {
            "x": 14.3,
            "y": 0.66,
            "z": -2.0
        },
        "rotation": {
            "x": 0.0,
            "y": 50.79213435254442,
            "z": 0.0
        },
        "category": "bread",
        "id": 1627821,
        "affordance_points": []
    },
    {
        "$type": "set_mass",
        "id": 1627821,
        "mass": 10
    },
    {
        "$type": "scale_object",
        "id": 1627821,
        "scale_factor": {
            "x": 0.5,
            "y": 0.5,
            "z": 0.5
        }
    },
    {
        "$type": "add_object",
        "name": "b03_loafbread",
        "url": "file://local_asset/Linux/b03_loafbread",
        "scale_factor": 1.0,
        "position": {
            "x": 13.9,
            "y": 0.66,
            "z": -2.0
        },
        "rotation": {
            "x": 0.0,
            "y": 237.38169210212817,
            "z": 0.0
        },
        "category": "bread",
        "id": 6090287,
        "affordance_points": []
    },
    {
        "$type": "set_mass",
        "id": 6090287,
        "mass": 10
    },
    {
        "$type": "scale_object",
        "id": 6090287,
        "scale_factor": {
            "x": 0.5,
            "y": 0.5,
            "z": 0.5
        }
    },
    {
        "$type": "add_object",
        "name": "b01_croissant",
        "url": "file://local_asset/Linux/b01_croissant",
        "scale_factor": 1.0,
        "position": {
            "x": 15.7,
            "y": 0.33,
            "z": -2.0
        },
        "rotation": {
            "x": 0.0,
            "y": 12.543367241937858,
            "z": 0.0
        },
        "category": "croissant",
        "id": 16605563,
        "affordance_points": []
    },
    {
        "$type": "set_mass",
        "id": 16605563,
        "mass": 10
    },
    {
        "$type": "scale_object",
        "id": 16605563,
        "scale_factor": {
            "x": 0.8,
            "y": 0.8,
            "z": 0.8
        }
    },
    {
        "$type": "add_object",
        "name": "b01_croissant",
        "url": "file://local_asset/Linux/b01_croissant",
        "scale_factor": 1.0,
        "position": {
            "x": 16.099999999999998,
            "y": 0.99,
            "z": -2.0
        },
        "rotation": {
            "x": 0.0,
            "y": 110.83329811133041,
            "z": 0.0
        },
        "category": "croissant",
        "id": 14357792,
        "affordance_points": []
    },
    {
        "$type": "set_mass",
        "id": 14357792,
        "mass": 10
    },
    {
        "$type": "scale_object",
        "id": 14357792,
        "scale_factor": {
            "x": 0.8,
            "y": 0.8,
            "z": 0.8
        }
    },
    {
        "$type": "add_object",
        "name": "b03_burger",
        "url": "file://local_asset/Linux/b03_burger",
        "scale_factor": 0.1350851,
        "position": {
            "x": 14.3,
            "y": 0.33,
            "z": -2.0
        },
        "rotation": {
            "x": 0.0,
            "y": 138.5471936477047,
            "z": 0.0
        },
        "category": "sandwich",
        "id": 8801787,
        "affordance_points": []
    },
    {
        "$type": "set_mass",
        "id": 8801787,
        "mass": 10
    },
    {
        "$type": "scale_object",
        "id": 8801787,
        "scale_factor": {
            "x": 1.2,
            "y": 1.2,
            "z": 1.2
        }
    },
    {
        "$type": "add_object",
        "name": "b03_burger",
        "url": "file://local_asset/Linux/b03_burger",
        "scale_factor": 0.1350851,
        "position": {
            "x": 15.7,
            "y": 0.99,
            "z": -2.0
        },
        "rotation": {
            "x": 0.0,
            "y": 176.12125483513154,
            "z": 0.0
        },
        "category": "sandwich",
        "id": 13048408,
        "affordance_points": []
    },
    {
        "$type": "set_mass",
        "id": 13048408,
        "mass": 10
    },
    {
        "$type": "scale_object",
        "id": 13048408,
        "scale_factor": {
            "x": 1.2,
            "y": 1.2,
            "z": 1.2
        }
    },
    {
        "$type": "add_object",
        "name": "b03_loafbread",
        "url": "file://local_asset/Linux/b03_loafbread",
        "scale_factor": 1.0,
        "position": {
            "x": 13.9,
            "y": 0.66,
            "z": 3.5
        },
        "rotation": {
            "x": 0.0,
            "y": 250.16053416865026,
            "z": 0.0
        },
        "category": "bread",
        "id": 16338283,
        "affordance_points": []
    },
    {
        "$type": "set_mass",
        "id": 16338283,
        "mass": 10
    },
    {
        "$type": "scale_object",
        "id": 16338283,
        "scale_factor": {
            "x": 0.5,
            "y": 0.5,
            "z": 0.5
        }
    },
    {
        "$type": "add_object",
        "name": "b01_croissant",
        "url": "file://local_asset/Linux/b01_croissant",
        "scale_factor": 1.0,
        "position": {
            "x": 15.7,
            "y": 0.66,
            "z": 3.5
        },
        "rotation": {
            "x": 0.0,
            "y": 74.71636295526412,
            "z": 0.0
        },
        "category": "croissant",
        "id": 14223469,
        "affordance_points": []
    },
    {
        "$type": "set_mass",
        "id": 14223469,
        "mass": 10
    },
    {
        "$type": "scale_object",
        "id": 14223469,
        "scale_factor": {
            "x": 0.8,
            "y": 0.8,
            "z": 0.8
        }
    },
    {
        "$type": "add_object",
        "name": "b03_pink_donuts_mesh",
        "url": "file://local_asset/Linux/b03_pink_donuts_mesh",
        "scale_factor": 2.079922,
        "position": {
            "x": 15.299999999999999,
            "y": 0.66,
            "z": 3.5
        },
        "rotation": {
            "x": 0.0,
            "y": 135.049477150588,
            "z": 0.0
        },
        "category": "donut",
        "id": 16090021,
        "affordance_points": []
    },
    {
        "$type": "set_mass",
        "id": 16090021,
        "mass": 10
    },
    {
        "$type": "scale_object",
        "id": 16090021,
        "scale_factor": {
            "x": 2.5,
            "y": 2.5,
            "z": 2.5
        }
    },
    {
        "$type": "add_object",
        "name": "b03_pink_donuts_mesh",
        "url": "file://local_asset/Linux/b03_pink_donuts_mesh",
        "scale_factor": 2.079922,
        "position": {
            "x": 14.700000000000001,
            "y": 0.66,
            "z": 3.5
        },
        "rotation": {
            "x": 0.0,
            "y": 209.97739907752444,
            "z": 0.0
        },
        "category": "donut",
        "id": 14128588,
        "affordance_points": []
    },
    {
        "$type": "set_mass",
        "id": 14128588,
        "mass": 10
    },
    {
        "$type": "scale_object",
        "id": 14128588,
        "scale_factor": {
            "x": 2.5,
            "y": 2.5,
            "z": 2.5
        }
    },
    {
        "$type": "add_object",
        "name": "102_pepsi_can_12_fl_oz_vray",
        "url": "file://local_asset/Linux/102_pepsi_can_12_fl_oz_vray",
        "scale_factor": 1.0,
        "position": {
            "x": 19.3,
            "y": 0.33,
            "z": -2.0
        },
        "rotation": {
            "x": 0.0,
            "y": 78.76881032003683,
            "z": 0.0
        },
        "category": "soda can",
        "id": 2514580,
        "affordance_points": []
    },
    {
        "$type": "set_mass",
        "id": 2514580,
        "mass": 10
    },
    {
        "$type": "scale_object",
        "id": 2514580,
        "scale_factor": {
            "x": 1.6,
            "y": 1.6,
            "z": 1.6
        }
    },
    {
        "$type": "add_object",
        "name": "102_pepsi_can_12_fl_oz_vray",
        "url": "file://local_asset/Linux/102_pepsi_can_12_fl_oz_vray",
        "scale_factor": 1.0,
        "position": {
            "x": 19.3,
            "y": 0.99,
            "z": -2.0
        },
        "rotation": {
            "x": 0.0,
            "y": 326.35499648250266,
            "z": 0.0
        },
        "category": "soda can",
        "id": 8188269,
        "affordance_points": []
    },
    {
        "$type": "set_mass",
        "id": 8188269,
        "mass": 10
    },
    {
        "$type": "scale_object",
        "id": 8188269,
        "scale_factor": {
            "x": 1.6,
            "y": 1.6,
            "z": 1.6
        }
    },
    {
        "$type": "add_object",
        "name": "104_sprite_can_12_fl_oz_vray",
        "url": "file://local_asset/Linux/104_sprite_can_12_fl_oz_vray",
        "scale_factor": 1.0,
        "position": {
            "x": 18.900000000000002,
            "y": 0.66,
            "z": -2.0
        },
        "rotation": {
            "x": 0.0,
            "y": 23.20438634243534,
            "z": 0.0
        },
        "category": "soda can",
        "id": 74613,
        "affordance_points": []
    },
    {
        "$type": "set_mass",
        "id": 74613,
        "mass": 10
    },
    {
        "$type": "scale_object",
        "id": 74613,
        "scale_factor": {
            "x": 1.6,
            "y": 1.6,
            "z": 1.6
        }
    },
    {
        "$type": "add_object",
        "name": "fanta_orange_can_12_fl_oz_vray",
        "url": "file://local_asset/Linux/fanta_orange_can_12_fl_oz_vray",
        "scale_factor": 1.0,
        "position": {
            "x": 19.7,
            "y": 0.33,
            "z": -2.0
        },
        "rotation": {
            "x": 0.0,
            "y": 208.95532388068023,
            "z": 0.0
        },
        "category": "soda can",
        "id": 6505600,
        "affordance_points": []
    },
    {
        "$type": "set_mass",
        "id": 6505600,
        "mass": 10
    },
    {
        "$type": "scale_object",
        "id": 6505600,
        "scale_factor": {
            "x": 1.6,
            "y": 1.6,
            "z": 1.6
        }
    },
    {
        "$type": "add_object",
        "name": "fanta_orange_can_12_fl_oz_vray",
        "url": "file://local_asset/Linux/fanta_orange_can_12_fl_oz_vray",
        "scale_factor": 1.0,
        "position": {
            "x": 18.900000000000002,
            "y": 0.99,
            "z": -2.0
        },
        "rotation": {
            "x": 0.0,
            "y": 275.3735188461296,
            "z": 0.0
        },
        "category": "soda can",
        "id": 8219832,
        "affordance_points": []
    },
    {
        "$type": "set_mass",
        "id": 8219832,
        "mass": 10
    },
    {
        "$type": "scale_object",
        "id": 8219832,
        "scale_factor": {
            "x": 1.6,
            "y": 1.6,
            "z": 1.6
        }
    },
    {
        "$type": "add_object",
        "name": "b03_cocacola_can_cage",
        "url": "file://local_asset/Linux/b03_cocacola_can_cage",
        "scale_factor": 1.1,
        "position": {
            "x": 20.7,
            "y": 0.33,
            "z": 3.5
        },
        "rotation": {
            "x": 0.0,
            "y": 100.80925073793476,
            "z": 0.0
        },
        "category": "soda can",
        "id": 9139497,
        "affordance_points": []
    },
    {
        "$type": "set_mass",
        "id": 9139497,
        "mass": 10
    },
    {
        "$type": "scale_object",
        "id": 9139497,
        "scale_factor": {
            "x": 2.0,
            "y": 2.0,
            "z": 2.0
        }
    },
    {
        "$type": "add_object",
        "name": "b03_cocacola_can_cage",
        "url": "file://local_asset/Linux/b03_cocacola_can_cage",
        "scale_factor": 1.1,
        "position": {
            "x": 21.099999999999998,
            "y": 0.99,
            "z": 3.5
        },
        "rotation": {
            "x": 0.0,
            "y": 187.5822836640083,
            "z": 0.0
        },
        "category": "soda can",
        "id": 11757983,
        "affordance_points": []
    },
    {
        "$type": "set_mass",
        "id": 11757983,
        "mass": 10
    },
    {
        "$type": "scale_object",
        "id": 11757983,
        "scale_factor": {
            "x": 2.0,
            "y": 2.0,
            "z": 2.0
        }
    },
    {
        "$type": "add_object",
        "name": "b03_cocacola_can_cage",
        "url": "file://local_asset/Linux/b03_cocacola_can_cage",
        "scale_factor": 1.1,
        "position": {
            "x": 19.7,
            "y": 0.66,
            "z": 3.5
        },
        "rotation": {
            "x": 0.0,
            "y": 152.86651858084548,
            "z": 0.0
        },
        "category": "soda can",
        "id": 5387003,
        "affordance_points": []
    },
    {
        "$type": "set_mass",
        "id": 5387003,
        "mass": 10
    },
    {
        "$type": "scale_object",
        "id": 5387003,
        "scale_factor": {
            "x": 2.0,
            "y": 2.0,
            "z": 2.0
        }
    },
    {
        "$type": "add_object",
        "name": "104_sprite_can_12_fl_oz_vray",
        "url": "file://local_asset/Linux/104_sprite_can_12_fl_oz_vray",
        "scale_factor": 1.0,
        "position": {
            "x": 19.7,
            "y": 0.33,
            "z": 3.5
        },
        "rotation": {
            "x": 0.0,
            "y": 129.9637679068118,
            "z": 0.0
        },
        "category": "soda can",
        "id": 13379507,
        "affordance_points": []
    },
    {
        "$type": "set_mass",
        "id": 13379507,
        "mass": 10
    },
    {
        "$type": "scale_object",
        "id": 13379507,
        "scale_factor": {
            "x": 1.6,
            "y": 1.6,
            "z": 1.6
        }
    },
    {
        "$type": "add_object",
        "name": "104_sprite_can_12_fl_oz_vray",
        "url": "file://local_asset/Linux/104_sprite_can_12_fl_oz_vray",
        "scale_factor": 1.0,
        "position": {
            "x": 19.7,
            "y": 0.99,
            "z": 3.5
        },
        "rotation": {
            "x": 0.0,
            "y": 234.69315426930976,
            "z": 0.0
        },
        "category": "soda can",
        "id": 2011769,
        "affordance_points": []
    },
    {
        "$type": "set_mass",
        "id": 2011769,
        "mass": 10
    },
    {
        "$type": "scale_object",
        "id": 2011769,
        "scale_factor": {
            "x": 1.6,
            "y": 1.6,
            "z": 1.6
        }
    },
    {
        "$type": "add_object",
        "name": "fanta_orange_can_12_fl_oz_vray",
        "url": "file://local_asset/Linux/fanta_orange_can_12_fl_oz_vray",
        "scale_factor": 1.0,
        "position": {
            "x": 21.099999999999998,
            "y": 0.66,
            "z": 3.5
        },
        "rotation": {
            "x": 0.0,
            "y": 59.77563238328013,
            "z": 0.0
        },
        "category": "soda can",
        "id": 4103146,
        "affordance_points": []
    },
    {
        "$type": "set_mass",
        "id": 4103146,
        "mass": 10
    },
    {
        "$type": "scale_object",
        "id": 4103146,
        "scale_factor": {
            "x": 1.6,
            "y": 1.6,
            "z": 1.6
        }
    },
    {
        "$type": "add_object",
        "name": "b03_fire_hydrant",
        "url": "file://local_asset/Linux/b03_fire_hydrant",
        "scale_factor": 1.0,
        "position": {
            "x": 2.0,
            "y": 0.0,
            "z": 5.5
        },
        "rotation": {
            "x": 0.0,
            "y": 90.0,
            "z": 0.0
        },
        "category": "fire hydrant",
        "id": 12753743,
        "affordance_points": []
    },
    {
        "$type": "set_kinematic_state",
        "id": 12753743,
        "is_kinematic": true
    },
    {
        "$type": "add_object",
        "name": "huffy_nel_lusso_womens_cruiser_bike_2011vray",
        "url": "file://local_asset/Linux/huffy_nel_lusso_womens_cruiser_bike_2011vray",
        "scale_factor": 1.0,
        "position": {
            "x": 19.21150168217383,
            "y": 0.1,
            "z": 0.5930628711350674
        },
        "rotation": {
            "x": 0.0,
            "y": 0.0,
            "z": 0.0
        },
        "category": "bicycle",
        "id": 6041596,
        "affordance_points": [
            {
                "x": -0.10441650450229645,
                "y": 0.9543246030807495,
                "z": -0.33645111322402954
            },
            {
                "x": -0.10129550844430923,
                "y": 0.9553921222686768,
                "z": 0.32874616980552673
            }
        ]
    },
    {
        "$type": "set_kinematic_state",
        "id": 6041596,
        "is_kinematic": true
    },
    {
        "$type": "scale_object",
        "id": 6041596,
        "scale_factor": {
            "x": 1.2,
            "y": 1.2,
            "z": 1.2
        }
    },
    {
        "$type": "step_physics",
        "frames": 50
    }
]