{
    "agent": {
        "0": [
            17.519643988480997,
            0.1,
            -0.8783011245537453
        ],
        "1": [
            10.045993829656608,
            0.1,
            0.49514597701620433
        ],
        "2": [
            18.519643988480997,
            0.1,
            0.12169887544625468
        ]
    },
    "avatar": {
        "id": "teaser",
        "position": {
            "x": 27,
            "y": 5,
            "z": 0.7
        },
        "look_at": {
            "x": 0,
            "y": 0,
            "z": 0.7
        }
    },
    "mass_map": {
        "3756626": 10,
        "4552792": 10,
        "1855327": 10,
        "10312511": 10,
        "4394316": 10,
        "6924871": 10,
        "13354736": 10,
        "12390269": 10,
        "4385988": 10,
        "10926541": 10,
        "5142029": 10,
        "9868797": 10,
        "573318": 10,
        "15806943": 10,
        "6788901": 10,
        "3142199": 10,
        "15170970": 10,
        "2731298": 10,
        "1690316": 10,
        "15556334": 10,
        "7618096": 10,
        "8102441": 10,
        "968921": 10,
        "7650059": 10,
        "2194719": 10,
        "494442": 10,
        "14241694": 10,
        "11285072": 10,
        "7018199": 10,
        "6892575": 10,
        "4863266": 10,
        "15260818": 10,
        "14662672": 10,
        "172088": 10,
        "7051584": 10,
        "5859297": 10
    },
    "scene_id": 6,
    "task": {
        "goal_position_names": "fire hydrant",
        "goal_task": [
            [
                "apple",
                3
            ],
            [
                "b04_orange_00",
                3
            ],
            [
                "b04_red_grapes",
                3
            ],
            [
                "b03_banan_001",
                3
            ],
            [
                "102_pepsi_can_12_fl_oz_vray",
                1
            ]
        ],
        "container_names": [
            "basket_18inx18inx12iin_bamboo",
            "basket_18inx18inx12iin_wood_mesh",
            "basket_18inx18inx12iin_wicker"
        ],
        "task_kind": "outdoor_shopping",
        "constraint_type": "riding"
    },
    "bike_id": 15872115
}